[{"user_id": "u-lZXCUgpBBsnbN7926Y3g0A", "name": "Violet", "fans": 0, "review_count": 6, "average_stars": 2.5, "friends": [], "gender": "female", "age": 56}, {"user_id": "u-GUMxq_mi_XFoUMlYDoQYeg", "name": "Sam", "fans": 0, "review_count": 40, "average_stars": 3.26, "friends": [], "gender": "male", "age": 35}, {"user_id": "u-BP0Qe_iFslyq7t6Xugvzrg", "name": "Shawn", "fans": 0, "review_count": 24, "average_stars": 3.88, "friends": [], "gender": "male", "age": 45}, {"user_id": "u-gyS1Ef3KamhVeyFhk4nqeQ", "name": "Marie", "fans": 0, "review_count": 11, "average_stars": 3.42, "friends": [], "gender": "female", "age": 25}, {"user_id": "u-bgjERvfhhgeDurSi9Ni5gg", "name": "Thomas", "fans": 0, "review_count": 34, "average_stars": 3.31, "friends": [], "gender": "male", "age": 1}, {"user_id": "u-pZsVUkMb4yGMGoTRzNS7Ew", "name": "Priyam", "fans": 8, "review_count": 93, "average_stars": 3.51, "friends": [], "gender": "male", "age": 35}, {"user_id": "u--dEAguztpqPvzftWb_YNdA", "name": "John", "fans": 0, "review_count": 8, "average_stars": 4.63, "friends": [], "gender": "male", "age": 56}, {"user_id": "u-71tacONUReSQ1tv2Edz4OQ", "name": "Katya", "fans": 5, "review_count": 109, "average_stars": 4.59, "friends": [], "gender": "female", "age": 56}, {"user_id": "u-Uaqawx2iD0mT5YP_akJrJw", "name": "Heli", "fans": 1, "review_count": 35, "average_stars": 3.23, "friends": [], "gender": "female", "age": 35}, {"user_id": "u-pj7M1RIWV0caCp7Kj91JxA", "name": "Adnan", "fans": 0, "review_count": 5, "average_stars": 3.5, "friends": [], "gender": "male", "age": 56}, {"user_id": "u-TMV_sdcRAzmgByr2ez6dAw", "name": "D", "fans": 0, "review_count": 5, "average_stars": 2.8, "friends": [], "gender": "female", "age": 56}, {"user_id": "u-zSaIbSCTB9ug09pOqf8_vw", "name": "Mich", "fans": 0, "review_count": 2, "average_stars": 1.0, "friends": [], "gender": "female", "age": 45}, {"user_id": "u-BSu2hEtBYvtADAEKiQrmiQ", "name": "Atif", "fans": 2, "review_count": 50, "average_stars": 4.3, "friends": [], "gender": "male", "age": 25}, {"user_id": "u-hTmPK8GhGXOKgFig4pMNmA", "name": "Lisa", "fans": 1, "review_count": 7, "average_stars": 4.86, "friends": [], "gender": "female", "age": 35}, {"user_id": "u-ZsisQjLoliFocSnktH3lsw", "name": "Mobahil", "fans": 0, "review_count": 1, "average_stars": 5.0, "friends": [], "gender": "female", "age": 25}, {"user_id": "u-W37KqgMymarQaqYGOWS70w", "name": "Burcu", "fans": 7, "review_count": 253, "average_stars": 3.7, "friends": [], "gender": "female", "age": 25}, {"user_id": "u-xCAwgus9fWEIrv5GvwykEQ", "name": "Faraz", "fans": 4, "review_count": 45, "average_stars": 4.15, "friends": [], "gender": "female", "age": 25}, {"user_id": "u-AJpmz9nHVf-Prm5l0U0bNw", "name": "Zulfiqar", "fans": 0, "review_count": 9, "average_stars": 2.11, "friends": [], "gender": "male", "age": 25}, {"user_id": "u-fNqVLJ6l19eqJaMV-hk-xw", "name": "Jay", "fans": 0, "review_count": 14, "average_stars": 3.29, "friends": [], "gender": "male", "age": 56}, {"user_id": "u-6T2wUKXuQkbk8vTwTC6OVQ", "name": "yasir", "fans": 0, "review_count": 1, "average_stars": 1.0, "friends": [], "gender": "female", "age": 56}, {"user_id": "u-ZDAjNnzMh_k_NPxYA0AwiQ", "name": "Sumra", "fans": 0, "review_count": 21, "average_stars": 3.95, "friends": [], "gender": "female", "age": 35}, {"user_id": "u-dzkWjkKZEFwibAx8aGNLqA", "name": "Akash", "fans": 0, "review_count": 7, "average_stars": 4.43, "friends": [], "gender": "male", "age": 56}, {"user_id": "u-a0m28ex8jW6PvnyojchLyw", "name": "Muneeb", "fans": 1, "review_count": 5, "average_stars": 2.17, "friends": [], "gender": "female", "age": 45}, {"user_id": "u-V_pw1PPGe6YbRl4-JpXfYQ", "name": "Aneesa", "fans": 0, "review_count": 1, "average_stars": 1.0, "friends": [], "gender": "male", "age": 18}, {"user_id": "u-n4DeNymCmaulmpoThjjEQg", "name": "Yelp", "fans": 0, "review_count": 18, "average_stars": 3.0, "friends": [], "gender": "female", "age": 45}, {"user_id": "u-Jai6ZKPwMwIOEh8mqI8JoQ", "name": "Stanley", "fans": 0, "review_count": 1, "average_stars": 4.0, "friends": [], "gender": "male", "age": 25}, {"user_id": "u-2p7wg_4xvgs8nWLkrU-puQ", "name": "Alex", "fans": 0, "review_count": 2, "average_stars": 1.0, "friends": [], "gender": "male", "age": 35}, {"user_id": "u-RRhco4irDXPk5EJmvuwr2w", "name": "Ish", "fans": 0, "review_count": 32, "average_stars": 3.06, "friends": [], "gender": "female", "age": 35}, {"user_id": "u-JT9Ux1QWW2x1tDyFNaSp1A", "name": "YC", "fans": 0, "review_count": 31, "average_stars": 3.29, "friends": [], "gender": "female", "age": 25}, {"user_id": "u-77bSr4yTJrt__livHS3CKA", "name": "Sriram", "fans": 0, "review_count": 6, "average_stars": 1.67, "friends": [], "gender": "female", "age": 35}, {"user_id": "u-xW6g0EMGxUqouRTzd0PItA", "name": "Jay", "fans": 0, "review_count": 16, "average_stars": 2.75, "friends": [], "gender": "male", "age": 25}, {"user_id": "u-ulM0B0JOkRDNLdZW3-rvFA", "name": "Ali", "fans": 9, "review_count": 119, "average_stars": 3.46, "friends": [], "gender": "male", "age": 18}, {"user_id": "u-O4Dim1eKErdBdKWUGpMxvQ", "name": "David", "fans": 2, "review_count": 129, "average_stars": 3.5, "friends": [], "gender": "male", "age": 35}, {"user_id": "u-8h6eKv00bmef5fExt7EWgg", "name": "Louis", "fans": 0, "review_count": 5, "average_stars": 3.0, "friends": [], "gender": "male", "age": 45}, {"user_id": "u-3W0lgVuuBCYpQqzy563WLQ", "name": "Abu", "fans": 0, "review_count": 2, "average_stars": 1.0, "friends": [], "gender": "male", "age": 35}, {"user_id": "u-CvJG4MAs3aVY8O2BuVKARg", "name": "Kavi", "fans": 5, "review_count": 66, "average_stars": 3.73, "friends": [], "gender": "female", "age": 35}, {"user_id": "u-1ho5Y8iaj73Ak3i1fUCePg", "name": "Andrew", "fans": 0, "review_count": 1, "average_stars": 3.0, "friends": [], "gender": "male", "age": 45}, {"user_id": "u-P41ptyME4S7rLnejVGJmUA", "name": "Kimon", "fans": 0, "review_count": 6, "average_stars": 3.0, "friends": [], "gender": "female", "age": 45}, {"user_id": "u-JrXC_MDp38BWwLn2SFdNsA", "name": "Phillip", "fans": 33, "review_count": 743, "average_stars": 3.77, "friends": [], "gender": "male", "age": 25}, {"user_id": "u-m66JEwIVUq_uQU06nWFHYA", "name": "Kevin", "fans": 0, "review_count": 16, "average_stars": 3.75, "friends": [], "gender": "male", "age": 25}, {"user_id": "u-Ul42L3SbNiV0aB1eocj-KQ", "name": "Utpala", "fans": 0, "review_count": 13, "average_stars": 4.69, "friends": ["u-cZm0eIvfPC7zxOwbKsjMLg"], "gender": "female", "age": 35}, {"user_id": "u-efK-KZ_2IuqtS1RoiWdy5w", "name": "Gautram", "fans": 0, "review_count": 28, "average_stars": 4.0, "friends": [], "gender": "female", "age": 18}, {"user_id": "u--P4MdxIwar7DCEiOpD_GkQ", "name": "Khadija", "fans": 2, "review_count": 47, "average_stars": 3.67, "friends": [], "gender": "female", "age": 18}, {"user_id": "u-pv8KCVEQ-nP9qyDP7YtXcw", "name": "Julie", "fans": 2, "review_count": 45, "average_stars": 3.83, "friends": [], "gender": "female", "age": 45}, {"user_id": "u-auxU8_xmF9Bi-sRD962_cA", "name": "I.T.", "fans": 1, "review_count": 20, "average_stars": 3.4, "friends": [], "gender": "female", "age": 35}, {"user_id": "u-JYxejNDBlyiQJQDVi4HCWA", "name": "James", "fans": 0, "review_count": 19, "average_stars": 1.19, "friends": [], "gender": "male", "age": 18}, {"user_id": "u-S3h-0vC4OwyahD0idAIdRQ", "name": "Elwood", "fans": 3, "review_count": 19, "average_stars": 3.16, "friends": [], "gender": "male", "age": 56}, {"user_id": "u-LwYZnGzCfpejTbjqcxj2Rw", "name": "John", "fans": 0, "review_count": 12, "average_stars": 4.31, "friends": [], "gender": "male", "age": 45}, {"user_id": "u-F0OeMvB1YTr0IJf-5CexZQ", "name": "Sunny", "fans": 0, "review_count": 16, "average_stars": 4.06, "friends": [], "gender": "male", "age": 25}, {"user_id": "u-cZm0eIvfPC7zxOwbKsjMLg", "name": "Umakant", "fans": 0, "review_count": 5, "average_stars": 4.6, "friends": ["u-Ul42L3SbNiV0aB1eocj-KQ"], "gender": "female", "age": 35}, {"user_id": "u-l6kkFLWO6FuEzRro6bcMwQ", "name": "Anmol", "fans": 1, "review_count": 128, "average_stars": 3.68, "friends": [], "gender": "female", "age": 35}, {"user_id": "u-lGe6PJ4T3IrgmYkM4SFMRQ", "name": "Dip", "fans": 0, "review_count": 1, "average_stars": 5.0, "friends": [], "gender": "male", "age": 35}, {"user_id": "u-FRnNgOvEWJvxo7h9np3RSw", "name": "Ainy", "fans": 1, "review_count": 8, "average_stars": 3.22, "friends": [], "gender": "female", "age": 45}, {"user_id": "u--9RU4LuI_TfYgv9rBijJoQ", "name": "Keith", "fans": 9, "review_count": 134, "average_stars": 3.98, "friends": [], "gender": "male", "age": 45}, {"user_id": "u-YCdNTtZEhQwmCbUk4skNlg", "name": "Paul", "fans": 0, "review_count": 44, "average_stars": 3.78, "friends": [], "gender": "male", "age": 25}, {"user_id": "u-12WATd_fLodHu2woJvHe6w", "name": "Janna", "fans": 0, "review_count": 7, "average_stars": 3.86, "friends": [], "gender": "female", "age": 35}, {"user_id": "u-5loLFO6EKKU_0czmJ0djEA", "name": "Kashif", "fans": 0, "review_count": 6, "average_stars": 1.0, "friends": [], "gender": "male", "age": 18}, {"user_id": "u-jnB_saJqNfOmVoCWquhAzg", "name": "Bilal", "fans": 73, "review_count": 1183, "average_stars": 3.69, "friends": [], "gender": "male", "age": 56}, {"user_id": "u-U5YQX_vMl_xQy8EQDqlNQQ", "name": "Stephanie", "fans": 207, "review_count": 1503, "average_stars": 3.49, "friends": [], "gender": "female", "age": 45}, {"user_id": "u-5Dw8l-8pBUGAenTqgLLe-A", "name": "Nidha", "fans": 0, "review_count": 5, "average_stars": 3.56, "friends": [], "gender": "male", "age": 18}, {"user_id": "u-nLADCnXaYRlx4jYJcHcGdA", "name": "Ali", "fans": 14, "review_count": 126, "average_stars": 3.16, "friends": [], "gender": "male", "age": 25}, {"user_id": "u-i-gDfcrFLVhrNhBCUAhFpg", "name": "Ayesha", "fans": 14, "review_count": 255, "average_stars": 3.95, "friends": [], "gender": "female", "age": 18}, {"user_id": "u-QOk29S8eOtu94j1uTpmsuQ", "name": "Daniel", "fans": 1, "review_count": 32, "average_stars": 3.61, "friends": [], "gender": "male", "age": 56}, {"user_id": "u-EpRIX7o1AC0JeQgwbYVbwQ", "name": "Harry", "fans": 0, "review_count": 3, "average_stars": 5.0, "friends": [], "gender": "male", "age": 25}, {"user_id": "u-hFfD_E7xWYtCNhMPfBYJJQ", "name": "Jared", "fans": 0, "review_count": 12, "average_stars": 4.0, "friends": [], "gender": "male", "age": 25}, {"user_id": "u-14ryIRc7Rh4N_oHgbqpTFQ", "name": "Anastassios", "fans": 0, "review_count": 5, "average_stars": 3.4, "friends": [], "gender": "male", "age": 56}, {"user_id": "u-5KuLnYyRHAeVkwsB1Iglug", "name": "Mehvish", "fans": 2, "review_count": 32, "average_stars": 3.2, "friends": [], "gender": "male", "age": 1}, {"user_id": "u-Zj-mjHHSliTJqv9a3WiXIg", "name": "Kishan", "fans": 1, "review_count": 39, "average_stars": 3.78, "friends": [], "gender": "male", "age": 25}, {"user_id": "u-849Kov2nwyTcSQ6mnA7oBQ", "name": "Jay", "fans": 0, "review_count": 30, "average_stars": 3.14, "friends": [], "gender": "male", "age": 45}, {"user_id": "u-KDGywMWT8L1oy6pOrWtFpQ", "name": "Syed", "fans": 4, "review_count": 154, "average_stars": 3.09, "friends": [], "gender": "male", "age": 18}, {"user_id": "u-SNkleqoSgBMP24WEwp9tSQ", "name": "Maanu", "fans": 0, "review_count": 11, "average_stars": 3.25, "friends": [], "gender": "female", "age": 35}, {"user_id": "u-JDEhGFIPAyIMkfHD0G13UA", "name": "Jamal", "fans": 5, "review_count": 152, "average_stars": 3.4, "friends": [], "gender": "male", "age": 56}, {"user_id": "u-HhXSYa7Wd0qRY_bRaAEfCw", "name": "M", "fans": 0, "review_count": 42, "average_stars": 3.1, "friends": [], "gender": "female", "age": 25}, {"user_id": "u-UGXxwHQCIMyvbBpn-ZDNDA", "name": "Suthan", "fans": 0, "review_count": 8, "average_stars": 3.22, "friends": [], "gender": "female", "age": 18}, {"user_id": "u-9pwWm2KOTjjK8Sfq3TB9YQ", "name": "Ryan", "fans": 0, "review_count": 22, "average_stars": 4.91, "friends": [], "gender": "male", "age": 25}, {"user_id": "u-NjP5TCZ_44ROxw41vYWAfQ", "name": "Zem", "fans": 0, "review_count": 4, "average_stars": 3.6, "friends": [], "gender": "female", "age": 35}, {"user_id": "u-RUEFu7mB6ZMQK550xhnbdw", "name": "Naureen", "fans": 10, "review_count": 231, "average_stars": 4.04, "friends": [], "gender": "male", "age": 35}, {"user_id": "u-1KJ_2hP6dDiCCOSUrx6i8Q", "name": "Bijal", "fans": 0, "review_count": 30, "average_stars": 4.22, "friends": [], "gender": "female", "age": 1}, {"user_id": "u-70c9g3Ii74HA8ATQxC215g", "name": "Linda", "fans": 0, "review_count": 1, "average_stars": 1.0, "friends": [], "gender": "female", "age": 25}, {"user_id": "u-8j44v53fSpg2VkCC1xWBnA", "name": "Gurnam", "fans": 0, "review_count": 10, "average_stars": 3.0, "friends": [], "gender": "male", "age": 18}, {"user_id": "u-zuFF5CTsZkacie2X7RP-0A", "name": "James", "fans": 4, "review_count": 178, "average_stars": 3.85, "friends": [], "gender": "male", "age": 35}, {"user_id": "u-_uyl_vUs7HEhuif8yBmLyQ", "name": "Jen", "fans": 10, "review_count": 113, "average_stars": 3.61, "friends": [], "gender": "female", "age": 25}, {"user_id": "u-xhsMa1qTepw6gpGF_nsXkA", "name": "Anna", "fans": 0, "review_count": 5, "average_stars": 2.0, "friends": [], "gender": "female", "age": 25}, {"user_id": "u-CMFuzmaDyJPh-CPL5kUbCg", "name": "Kashif", "fans": 0, "review_count": 30, "average_stars": 3.4, "friends": [], "gender": "male", "age": 18}, {"user_id": "u-v5cmRSLLg2cDBspggFgX0w", "name": "Rajan", "fans": 0, "review_count": 16, "average_stars": 4.06, "friends": [], "gender": "male", "age": 25}, {"user_id": "u-q9ZzaDBNs72WXqKkwELBNA", "name": "Soumya", "fans": 0, "review_count": 3, "average_stars": 2.0, "friends": [], "gender": "female", "age": 35}, {"user_id": "u-ru2Sp_BdKZF-rnAQdt2g6w", "name": "Nurali", "fans": 0, "review_count": 22, "average_stars": 3.57, "friends": [], "gender": "male", "age": 35}, {"user_id": "u-vrmKjuRXl57PZr3NdyqOGQ", "name": "Anjum", "fans": 0, "review_count": 1, "average_stars": 1.0, "friends": [], "gender": "female", "age": 56}, {"user_id": "u-Q4W700OKMIR8wtj0V-CAjA", "name": "H", "fans": 0, "review_count": 10, "average_stars": 3.1, "friends": [], "gender": "female", "age": 25}, {"user_id": "u-rVi5NvoVDH3Lyk0HPFGdRQ", "name": "Ayaz", "fans": 0, "review_count": 13, "average_stars": 2.16, "friends": [], "gender": "male", "age": 45}, {"user_id": "u-YuYhr9rAxJzEE2-4JxxTQQ", "name": "Elisha", "fans": 0, "review_count": 4, "average_stars": 3.0, "friends": [], "gender": "male", "age": 35}, {"user_id": "u-SG11s8Gtcb5qGsABaXKvAg", "name": "Nita", "fans": 0, "review_count": 1, "average_stars": 1.0, "friends": [], "gender": "female", "age": 56}, {"user_id": "u-2SeI7d6epQoFyGUzrPkzUw", "name": "Yasmeen", "fans": 1, "review_count": 80, "average_stars": 2.88, "friends": [], "gender": "male", "age": 56}, {"user_id": "u-2rcc5LNa6DUA7PlUJZX0GA", "name": "Marianne", "fans": 7, "review_count": 45, "average_stars": 3.98, "friends": [], "gender": "female", "age": 18}, {"user_id": "u-mOVyk3O18VY5nrUMTZgM1w", "name": "Ankita", "fans": 44, "review_count": 342, "average_stars": 3.71, "friends": [], "gender": "male", "age": 45}, {"user_id": "u-ng1ccHLnRGqGuMG_KXziaA", "name": "Eric", "fans": 1, "review_count": 10, "average_stars": 3.0, "friends": [], "gender": "male", "age": 25}, {"user_id": "u-cCDZ9jIVumYIb8KrhpDAFQ", "name": "Rajinthan", "fans": 0, "review_count": 1, "average_stars": 5.0, "friends": [], "gender": "female", "age": 35}, {"user_id": "u-8q4qgrHmNn2OHLb8g3nHGQ", "name": "Alka", "fans": 6, "review_count": 284, "average_stars": 3.91, "friends": ["u-zuFF5CTsZkacie2X7RP-0A"], "gender": "female", "age": 45}, {"user_id": "u-whi_8onFyy-kR8-3qubApQ", "name": "Brittany", "fans": 0, "review_count": 1, "average_stars": 1.0, "friends": [], "gender": "female", "age": 35}, {"user_id": "u-CtvxL2SA-Wn0Tt-Ov1dJwQ", "name": "John", "fans": 12, "review_count": 293, "average_stars": 3.91, "friends": [], "gender": "male", "age": 35}, {"user_id": "u-WX5KfRMzgSIjA_dbkrGnLw", "name": "Jon", "fans": 0, "review_count": 1, "average_stars": 1.0, "friends": [], "gender": "male", "age": 35}, {"user_id": "u-CY7Mtn1xuifQrI2S96BaQQ", "name": "Charlotte", "fans": 1, "review_count": 15, "average_stars": 3.25, "friends": [], "gender": "female", "age": 35}, {"user_id": "u-Ug0ujy9-jd0Oc2nk3KIotA", "name": "Messer", "fans": 221, "review_count": 2244, "average_stars": 4.5, "friends": [], "gender": "female", "age": 1}, {"user_id": "u-jF6BdhSNhnaOVfleA8GN1A", "name": "Patrick", "fans": 0, "review_count": 2, "average_stars": 3.5, "friends": [], "gender": "male", "age": 1}, {"user_id": "u-viDOnsL8pW6A-HEAf_VXXQ", "name": "Ritesh", "fans": 0, "review_count": 9, "average_stars": 3.22, "friends": [], "gender": "female", "age": 56}, {"user_id": "u--RDIhvdYrhOAqDF232pCnw", "name": "Shilpa", "fans": 0, "review_count": 7, "average_stars": 4.38, "friends": [], "gender": "female", "age": 25}, {"user_id": "u-fZoXZmSR-xnpjG5zi7ALrQ", "name": "Arpit", "fans": 0, "review_count": 22, "average_stars": 3.96, "friends": [], "gender": "female", "age": 45}, {"user_id": "u-SHqmk_PNFRlPpJjeYFO0eg", "name": "Ma", "fans": 0, "review_count": 5, "average_stars": 1.6, "friends": [], "gender": "female", "age": 35}, {"user_id": "u-U96FpJ6l1IcM4h8iMwmHgA", "name": "Rick", "fans": 1, "review_count": 91, "average_stars": 3.5, "friends": [], "gender": "male", "age": 35}, {"user_id": "u-at6V9uGBsF66j-zdylJUPQ", "name": "U", "fans": 0, "review_count": 15, "average_stars": 2.56, "friends": [], "gender": "female", "age": 35}, {"user_id": "u-kcZ79VN2n0PmBbpWv6Ayqw", "name": "Stephen", "fans": 0, "review_count": 2, "average_stars": 1.5, "friends": [], "gender": "male", "age": 45}, {"user_id": "u-gGCv9qdMRgAa39ao0Phr7g", "name": "Jonathan", "fans": 7, "review_count": 113, "average_stars": 3.76, "friends": [], "gender": "male", "age": 56}, {"user_id": "u-2HD29DRmkH3ZzJq-emARJQ", "name": "Dusty", "fans": 1, "review_count": 3, "average_stars": 3.0, "friends": [], "gender": "male", "age": 18}, {"user_id": "u-eVWh6Wzt9R-DkFZ-xoj1xw", "name": "Tessa", "fans": 0, "review_count": 35, "average_stars": 4.58, "friends": [], "gender": "female", "age": 45}, {"user_id": "u-M4LkknfZPebvUfzWUrNYBw", "name": "Linda", "fans": 0, "review_count": 13, "average_stars": 2.62, "friends": [], "gender": "female", "age": 35}, {"user_id": "u-uH2bJ1_c8Q_cUgKQFZEowg", "name": "Atul", "fans": 0, "review_count": 8, "average_stars": 3.63, "friends": [], "gender": "male", "age": 45}, {"user_id": "u-JEl_9-vznwpcj0fKRXNc0g", "name": "Laura", "fans": 0, "review_count": 1, "average_stars": 2.0, "friends": [], "gender": "female", "age": 45}, {"user_id": "u-9aDdvrXmoMC2PbJQPVO8GQ", "name": "Carol", "fans": 0, "review_count": 47, "average_stars": 4.08, "friends": [], "gender": "female", "age": 25}, {"user_id": "u-RD9rnr0uNtYJya-pl21fbg", "name": "Andrew", "fans": 0, "review_count": 6, "average_stars": 2.67, "friends": [], "gender": "male", "age": 45}, {"user_id": "u-7uNESKhTlge7kCN00u5LPQ", "name": "Alyssa", "fans": 23, "review_count": 158, "average_stars": 4.18, "friends": [], "gender": "female", "age": 18}, {"user_id": "u-YEDnTf7d6RyXKEHDGqi9tg", "name": "Sume", "fans": 18, "review_count": 192, "average_stars": 4.05, "friends": [], "gender": "female", "age": 35}, {"user_id": "u-ONRLfyEi7-exqKlfWiRC4A", "name": "Tahiyeh", "fans": 0, "review_count": 10, "average_stars": 2.55, "friends": [], "gender": "female", "age": 35}, {"user_id": "u-LVgkbdEsYiYLTK7dAYmAMQ", "name": "Wernm-f", "fans": 0, "review_count": 1, "average_stars": 1.0, "friends": [], "gender": "female", "age": 45}, {"user_id": "u-sfKwAw0FD8KuWp4Hjv0cxQ", "name": "Will", "fans": 9, "review_count": 88, "average_stars": 3.67, "friends": [], "gender": "male", "age": 25}, {"user_id": "u-jugdbQsk3vj05c1Kn5aa4g", "name": "Shawn", "fans": 0, "review_count": 5, "average_stars": 2.6, "friends": [], "gender": "male", "age": 25}, {"user_id": "u-PdBWNah2YanRXEZovFPwIw", "name": "Thuraya", "fans": 0, "review_count": 9, "average_stars": 3.11, "friends": [], "gender": "female", "age": 35}, {"user_id": "u-wXdL__0_Vd53Q8U-tOKXEQ", "name": "Eddie", "fans": 0, "review_count": 6, "average_stars": 2.5, "friends": [], "gender": "male", "age": 45}, {"user_id": "u-cpy2Ws6btVpbMvZ3Ioqw6w", "name": "Tasmina", "fans": 0, "review_count": 20, "average_stars": 3.22, "friends": [], "gender": "male", "age": 1}, {"user_id": "u-uJ8vU_PYpcj9V8_wGfGyhg", "name": "Pierre", "fans": 0, "review_count": 5, "average_stars": 2.0, "friends": [], "gender": "male", "age": 45}, {"user_id": "u-rlqSOqnC4IDP612W2DlYLw", "name": "Asif", "fans": 0, "review_count": 10, "average_stars": 2.6, "friends": [], "gender": "male", "age": 18}, {"user_id": "u-_1SKSmLqpHBqWh09DxQMfw", "name": "A.J.", "fans": 181, "review_count": 794, "average_stars": 3.49, "friends": [], "gender": "female", "age": 1}, {"user_id": "u-1xgOoQxczEEsYuH1YFMZog", "name": "Kiki", "fans": 0, "review_count": 36, "average_stars": 3.49, "friends": [], "gender": "female", "age": 56}, {"user_id": "u-T7cNF1q6PSV5mOs4r2-rrA", "name": "Tom", "fans": 0, "review_count": 49, "average_stars": 4.17, "friends": [], "gender": "male", "age": 35}, {"user_id": "u-986D6wn2BiPvscg-kLLGJA", "name": "Christina", "fans": 0, "review_count": 4, "average_stars": 4.0, "friends": [], "gender": "female", "age": 35}, {"user_id": "u-Hn9nTEOEjOyHbS3KtesquQ", "name": "Adrian", "fans": 0, "review_count": 22, "average_stars": 3.64, "friends": [], "gender": "male", "age": 25}, {"user_id": "u-waffoafSdOleXdxQtkwxxg", "name": "Suraz", "fans": 0, "review_count": 1, "average_stars": 5.0, "friends": [], "gender": "female", "age": 56}, {"user_id": "u-O_P3ht6XRpd2DE6J55PANQ", "name": "Steph", "fans": 1, "review_count": 3, "average_stars": 3.67, "friends": [], "gender": "female", "age": 1}, {"user_id": "u-q5OhW8ne_hteHo6xLHNUPg", "name": "Bon'shaniqua", "fans": 3, "review_count": 118, "average_stars": 3.77, "friends": [], "gender": "female", "age": 45}, {"user_id": "u-47R5xhLhoprA8xYkS21x9Q", "name": "Isa", "fans": 0, "review_count": 4, "average_stars": 3.2, "friends": [], "gender": "female", "age": 25}, {"user_id": "u-QIC7YDWVIciSHX9FQHa-3g", "name": "Suvi", "fans": 0, "review_count": 7, "average_stars": 3.43, "friends": ["u-rLafRDi22mMbZlBTDbZlBA"], "gender": "female", "age": 25}, {"user_id": "u-6ymZbkJ7vt8eGHA7bHlONg", "name": "Amanda", "fans": 1, "review_count": 31, "average_stars": 3.39, "friends": [], "gender": "female", "age": 35}, {"user_id": "u-zFGpxwJewI6OjC2u9EnZ-g", "name": "Dina", "fans": 1, "review_count": 141, "average_stars": 3.85, "friends": [], "gender": "female", "age": 35}, {"user_id": "u-pZVxKioyk_4KBquQpwgP9Q", "name": "Beth", "fans": 0, "review_count": 13, "average_stars": 3.62, "friends": [], "gender": "female", "age": 25}, {"user_id": "u-kB9QPxar7HLKIpK7qeMnFA", "name": "Josephine", "fans": 11, "review_count": 239, "average_stars": 3.65, "friends": [], "gender": "female", "age": 25}, {"user_id": "u-1ZzOs18zciLBYMZ2cQv58A", "name": "Sarah", "fans": 1, "review_count": 55, "average_stars": 3.97, "friends": [], "gender": "female", "age": 18}, {"user_id": "u-pPEo1f_ikIP86DuiVTnmhg", "name": "Dalikes", "fans": 0, "review_count": 5, "average_stars": 5.0, "friends": [], "gender": "female", "age": 45}, {"user_id": "u-3GjCf5k5X219pDy5rYgxvQ", "name": "Ryan", "fans": 3, "review_count": 127, "average_stars": 3.66, "friends": [], "gender": "male", "age": 35}, {"user_id": "u-r_UQaRU3kiLD9xnwN40kjw", "name": "Nadeena", "fans": 0, "review_count": 7, "average_stars": 3.25, "friends": [], "gender": "male", "age": 1}, {"user_id": "u-U7tUoXPJhbf2k9fwrAhn5w", "name": "Carrie", "fans": 0, "review_count": 51, "average_stars": 3.98, "friends": [], "gender": "female", "age": 56}, {"user_id": "u-4dVgvYYgrem4rhz5CoBk6g", "name": "Michele", "fans": 3, "review_count": 52, "average_stars": 3.4, "friends": [], "gender": "female", "age": 25}, {"user_id": "u-vVHVLgvh2hSsglO4uGSEVg", "name": "Dil", "fans": 0, "review_count": 28, "average_stars": 3.61, "friends": [], "gender": "female", "age": 45}, {"user_id": "u-F21kxY7kQRQwlyvxpLZk6Q", "name": "Liza", "fans": 0, "review_count": 17, "average_stars": 3.47, "friends": [], "gender": "female", "age": 18}, {"user_id": "u-RmiKdzXAb9Ai8csbGCCO1g", "name": "Zubair", "fans": 1, "review_count": 17, "average_stars": 2.78, "friends": [], "gender": "female", "age": 35}, {"user_id": "u-PS57qKDqNUlsLlsOxF00qg", "name": "M", "fans": 1, "review_count": 92, "average_stars": 3.27, "friends": [], "gender": "female", "age": 56}, {"user_id": "u-iWKXKikPiPGr5bzeFlxA5w", "name": "TheOneMan", "fans": 0, "review_count": 7, "average_stars": 3.57, "friends": [], "gender": "female", "age": 56}, {"user_id": "u-5FMeJRjsn1zN9Y9q6X1uyw", "name": "R", "fans": 0, "review_count": 12, "average_stars": 1.92, "friends": [], "gender": "female", "age": 25}, {"user_id": "u-dzC95g6MT4ErmcKbiu6oTg", "name": "Joan", "fans": 5, "review_count": 287, "average_stars": 4.19, "friends": [], "gender": "female", "age": 18}, {"user_id": "u-oUL-6V1aBBjsD06pOamfSQ", "name": "Betty", "fans": 0, "review_count": 5, "average_stars": 3.2, "friends": [], "gender": "female", "age": 45}, {"user_id": "u-fnFU_41zyKA10bt3dgBFMw", "name": "Ashley", "fans": 0, "review_count": 17, "average_stars": 3.94, "friends": [], "gender": "female", "age": 18}, {"user_id": "u-8OZ0XguTupUeWpeAZ7u7MQ", "name": "Randus", "fans": 0, "review_count": 15, "average_stars": 4.19, "friends": [], "gender": "female", "age": 35}, {"user_id": "u-xwIeGfv2NAhq9Kofn5qQmg", "name": "Reena", "fans": 15, "review_count": 250, "average_stars": 3.79, "friends": [], "gender": "female", "age": 56}, {"user_id": "u-Bsbumyr3Of8BauN2URK4bg", "name": "Tonya", "fans": 165, "review_count": 515, "average_stars": 4.39, "friends": [], "gender": "female", "age": 18}, {"user_id": "u-QGOtNZfasBwWCuawKjypYA", "name": "Jacqueline", "fans": 45, "review_count": 946, "average_stars": 4.36, "friends": [], "gender": "female", "age": 35}, {"user_id": "u-NAOx8KnWeaCcbYN0VE-HSA", "name": "Jennifer", "fans": 0, "review_count": 13, "average_stars": 4.62, "friends": [], "gender": "female", "age": 35}, {"user_id": "u-pBeNjksmGLPlBTaujOqiLQ", "name": "Anthony", "fans": 10, "review_count": 153, "average_stars": 4.62, "friends": [], "gender": "male", "age": 35}, {"user_id": "u-egMzPypB0n9ZCq86ybRFpw", "name": "Andrew", "fans": 1, "review_count": 4, "average_stars": 4.75, "friends": [], "gender": "male", "age": 25}, {"user_id": "u-FflbpnSuF3POJG_lPdxLlg", "name": "Stephen", "fans": 0, "review_count": 4, "average_stars": 4.2, "friends": [], "gender": "male", "age": 45}, {"user_id": "u-dsXDA0Dwspk47FFhi3oKvg", "name": "Scott", "fans": 1, "review_count": 17, "average_stars": 2.05, "friends": [], "gender": "male", "age": 25}, {"user_id": "u-26APrhqCQ8pxzqWiMWwFcg", "name": "Hirie", "fans": 0, "review_count": 22, "average_stars": 3.91, "friends": [], "gender": "female", "age": 25}, {"user_id": "u-YscjZezxLirEjK_bK82uAw", "name": "Carol", "fans": 32, "review_count": 329, "average_stars": 4.33, "friends": ["u-E43QxgV87Ij6KxMCHcijKw"], "gender": "female", "age": 18}, {"user_id": "u-yiWOSHrLIliecmnzdZbxqA", "name": "Jamey", "fans": 0, "review_count": 16, "average_stars": 3.88, "friends": [], "gender": "male", "age": 45}, {"user_id": "u-qvPTw-ArHYI1n1n0cw3S7A", "name": "Michael", "fans": 41, "review_count": 408, "average_stars": 3.93, "friends": [], "gender": "male", "age": 35}, {"user_id": "u-3c3aNHGUPDwFZhxCe-p8Ag", "name": "Chris", "fans": 1, "review_count": 31, "average_stars": 4.66, "friends": [], "gender": "male", "age": 35}, {"user_id": "u-CgG6X3k3DGSL2RR3ekzfsA", "name": "Daniel", "fans": 5, "review_count": 123, "average_stars": 4.01, "friends": [], "gender": "male", "age": 35}, {"user_id": "u-FyikYazQbNoOumDooOQyyA", "name": "Lauren", "fans": 1, "review_count": 193, "average_stars": 3.74, "friends": [], "gender": "female", "age": 1}, {"user_id": "u-rSQITvDnm1smzJl-3LJz4Q", "name": "Jess", "fans": 30, "review_count": 405, "average_stars": 4.35, "friends": [], "gender": "male", "age": 18}, {"user_id": "u-xZIS0iyY463Pxv9_v8GBTg", "name": "Ajay", "fans": 103, "review_count": 43, "average_stars": 4.18, "friends": [], "gender": "male", "age": 18}, {"user_id": "u-E43QxgV87Ij6KxMCHcijKw", "name": "Nikki", "fans": 570, "review_count": 839, "average_stars": 4.1, "friends": [], "gender": "female", "age": 25}, {"user_id": "u-F-nLfSJ4qtdZRwNW993lSw", "name": "Abhishek", "fans": 0, "review_count": 9, "average_stars": 3.22, "friends": [], "gender": "female", "age": 45}, {"user_id": "u-eeHkL577GLoekAV9TsTTkA", "name": "Serena", "fans": 0, "review_count": 1, "average_stars": 5.0, "friends": [], "gender": "female", "age": 45}, {"user_id": "u-MNg6tOsLAKgxsdhLNK6iGg", "name": "Kiran Shane", "fans": 0, "review_count": 4, "average_stars": 4.5, "friends": [], "gender": "female", "age": 35}, {"user_id": "u-iVmBpLCIuUA0Hsu1eNKQ4g", "name": "Nav", "fans": 4, "review_count": 122, "average_stars": 4.01, "friends": [], "gender": "female", "age": 45}, {"user_id": "u-9c1gu4xbBbdwR6IxXkYlMQ", "name": "Valishti Artee", "fans": 0, "review_count": 9, "average_stars": 3.2, "friends": [], "gender": "female", "age": 18}, {"user_id": "u--p3a5JqLcVMIdiqxCsgmZw", "name": "Tony", "fans": 0, "review_count": 17, "average_stars": 4.53, "friends": [], "gender": "male", "age": 35}, {"user_id": "u-uCdmtWpEku3xLa-ScQabKA", "name": "Nadia", "fans": 10, "review_count": 212, "average_stars": 3.73, "friends": [], "gender": "female", "age": 56}, {"user_id": "u-VLfK0P4aHwCThv3h7GeQQw", "name": "Tamsyn", "fans": 9, "review_count": 144, "average_stars": 3.38, "friends": [], "gender": "female", "age": 35}, {"user_id": "u-QdLc74qpa5sXJOfgb0FthQ", "name": "Tariq", "fans": 0, "review_count": 6, "average_stars": 4.33, "friends": [], "gender": "male", "age": 35}, {"user_id": "u-PVyl_Kilc81Y0e3eCGJF0g", "name": "Candice", "fans": 8, "review_count": 62, "average_stars": 3.36, "friends": [], "gender": "female", "age": 25}, {"user_id": "u-3B7t3At5fFWaeLVaHiVk4A", "name": "Chris", "fans": 1, "review_count": 6, "average_stars": 4.0, "friends": [], "gender": "male", "age": 45}, {"user_id": "u-ufRKH6kV_n6h5lsmuOr5ig", "name": "Harpreet", "fans": 0, "review_count": 10, "average_stars": 2.4, "friends": [], "gender": "male", "age": 35}, {"user_id": "u-2tGL1SDJnK7GiH8c5yhSBQ", "name": "Chrissy", "fans": 14, "review_count": 201, "average_stars": 4.55, "friends": [], "gender": "female", "age": 35}, {"user_id": "u-xnLliq9Majlk9i0Orf7Iig", "name": "Aaron", "fans": 15, "review_count": 162, "average_stars": 3.73, "friends": ["u-y05H_1uQhO4frLTJ5_tGCQ"], "gender": "male", "age": 18}, {"user_id": "u-tIbL7mV0a0aOSg8ks4asnw", "name": "Sandra", "fans": 0, "review_count": 15, "average_stars": 3.33, "friends": [], "gender": "female", "age": 45}, {"user_id": "u-W66pmCWETd2cFnWT4Mrn3g", "name": "Ve", "fans": 3, "review_count": 47, "average_stars": 3.63, "friends": [], "gender": "female", "age": 45}, {"user_id": "u-7qSOf2kaMWEhS544oIFR4w", "name": "Shelley", "fans": 9, "review_count": 83, "average_stars": 4.01, "friends": [], "gender": "female", "age": 25}, {"user_id": "u-xG_UtKXuRR-vXcPsqbZm7w", "name": "Kimi", "fans": 1, "review_count": 149, "average_stars": 4.25, "friends": [], "gender": "female", "age": 1}, {"user_id": "u-rLafRDi22mMbZlBTDbZlBA", "name": "Nino", "fans": 4, "review_count": 118, "average_stars": 3.19, "friends": [], "gender": "male", "age": 18}, {"user_id": "u-R_TJQ6Hy1BtOYK_hCl25bQ", "name": "Joyce", "fans": 0, "review_count": 33, "average_stars": 3.66, "friends": [], "gender": "female", "age": 45}, {"user_id": "u-y05H_1uQhO4frLTJ5_tGCQ", "name": "Katelyn", "fans": 26, "review_count": 453, "average_stars": 3.76, "friends": [], "gender": "female", "age": 45}, {"user_id": "u-4L3W45S-ssdoKevuv5ykVw", "name": "Reem", "fans": 2, "review_count": 52, "average_stars": 3.0, "friends": [], "gender": "female", "age": 25}, {"user_id": "u-51_EJUsPW8NpsO8C9N4JqA", "name": "Mathanega", "fans": 6, "review_count": 123, "average_stars": 3.6, "friends": [], "gender": "female", "age": 45}, {"user_id": "u-eDKpiNOWoPqi3NFDn6QgEw", "name": "Trevor", "fans": 0, "review_count": 4, "average_stars": 3.4, "friends": [], "gender": "male", "age": 45}, {"user_id": "u-a2VgXrdJUflY9HOTPb62XA", "name": "Jamie", "fans": 0, "review_count": 10, "average_stars": 3.5, "friends": [], "gender": "female", "age": 25}, {"user_id": "u-z01bY3_w1GieMWOvQHznRA", "name": "Tammy", "fans": 1, "review_count": 35, "average_stars": 2.63, "friends": [], "gender": "female", "age": 1}, {"user_id": "u-Y1N7LPhi3xAq3UBLKWpWNQ", "name": "Anthony", "fans": 8, "review_count": 261, "average_stars": 2.95, "friends": [], "gender": "male", "age": 18}, {"user_id": "u-iIe1gtgyLqV0ZBbArDQkvg", "name": "Monica", "fans": 27, "review_count": 184, "average_stars": 3.7, "friends": [], "gender": "female", "age": 25}, {"user_id": "u-kQF9NmkkxmUTo3AUTfAvlA", "name": "Jun", "fans": 0, "review_count": 5, "average_stars": 3.4, "friends": ["u-DbvIS10e5BRB7AFT5DAW4Q"], "gender": "male", "age": 1}, {"user_id": "u-I8OgHOWhfyFsDPfC3YU3xw", "name": "San Jay", "fans": 0, "review_count": 1, "average_stars": 5.0, "friends": [], "gender": "female", "age": 25}, {"user_id": "u-idKkqBLI8MpwgTHm71t0PQ", "name": "Melwyn", "fans": 0, "review_count": 11, "average_stars": 3.36, "friends": [], "gender": "female", "age": 45}, {"user_id": "u-3p66LPQoaDIrA7fMoq9t8A", "name": "Am", "fans": 0, "review_count": 1, "average_stars": 3.0, "friends": [], "gender": "female", "age": 25}, {"user_id": "u-DbvIS10e5BRB7AFT5DAW4Q", "name": "Betty", "fans": 0, "review_count": 12, "average_stars": 3.5, "friends": [], "gender": "female", "age": 25}, {"user_id": "u-Vd6N3Dc9rtho-hOspaKQSg", "name": "Viola", "fans": 2, "review_count": 196, "average_stars": 3.27, "friends": [], "gender": "female", "age": 25}, {"user_id": "u-Xd-3racucNVUv1_SVxfvgQ", "name": "Karan", "fans": 0, "review_count": 16, "average_stars": 2.25, "friends": [], "gender": "female", "age": 25}, {"user_id": "u-iDBDdG29pE0963TYM0q-qg", "name": "Matt", "fans": 1, "review_count": 106, "average_stars": 3.68, "friends": [], "gender": "male", "age": 35}, {"user_id": "u-YtbE0S6-A6ls12cLhqueyw", "name": "Steven", "fans": 0, "review_count": 21, "average_stars": 4.05, "friends": [], "gender": "male", "age": 18}, {"user_id": "u-kEK448CBw3QYJy52cT6euQ", "name": "Meow", "fans": 0, "review_count": 18, "average_stars": 2.35, "friends": [], "gender": "female", "age": 35}, {"user_id": "u-yiZGdSHvIFY0tetpl2ZxPQ", "name": "Chris", "fans": 1, "review_count": 45, "average_stars": 2.88, "friends": [], "gender": "male", "age": 45}, {"user_id": "u-EFddU8cj_WTKTBFgdatFBA", "name": "Mohmoney2000", "fans": 0, "review_count": 15, "average_stars": 3.0, "friends": [], "gender": "female", "age": 56}, {"user_id": "u-j4iVWaHuwusa1vVAISWa5A", "name": "Pauline", "fans": 0, "review_count": 12, "average_stars": 4.33, "friends": [], "gender": "female", "age": 25}, {"user_id": "u-4KbUaerUBoiUwZGMHKVFxQ", "name": "Shaheed", "fans": 17, "review_count": 345, "average_stars": 3.66, "friends": [], "gender": "female", "age": 45}, {"user_id": "u-9p6B0BZhUREP4-Ua_xD4bA", "name": "Jeremy", "fans": 0, "review_count": 20, "average_stars": 3.3, "friends": [], "gender": "male", "age": 35}, {"user_id": "u-fVAtXHil33Mwk2vETayyUg", "name": "Anna", "fans": 0, "review_count": 1, "average_stars": 5.0, "friends": ["u-8b8tlDCc2HE9G7rLEMF2lg"], "gender": "female", "age": 25}, {"user_id": "u-65UXy9qtuLUI93cK8VcDxg", "name": "Harley", "fans": 0, "review_count": 20, "average_stars": 2.6, "friends": [], "gender": "male", "age": 35}, {"user_id": "u-fr5efb7JrVpFBF9q303NVQ", "name": "Ali", "fans": 2, "review_count": 137, "average_stars": 3.89, "friends": [], "gender": "male", "age": 18}, {"user_id": "u-iBofWBmQqEnXJAzQVuhS7Q", "name": "Winnie", "fans": 1, "review_count": 45, "average_stars": 4.46, "friends": [], "gender": "female", "age": 45}, {"user_id": "u-WRchgs4LvsIYidMhlkiCgw", "name": "Christian", "fans": 0, "review_count": 21, "average_stars": 4.77, "friends": [], "gender": "male", "age": 56}, {"user_id": "u-Ecqlb6gdkIjLlj92HUqilA", "name": "Paul", "fans": 0, "review_count": 8, "average_stars": 4.13, "friends": [], "gender": "male", "age": 45}, {"user_id": "u-5INcrkxpxXMbLP1VDBrP9w", "name": "Amanda", "fans": 0, "review_count": 39, "average_stars": 3.95, "friends": [], "gender": "female", "age": 25}, {"user_id": "u-SdXxLZQQnQNUEL1rGMOQ6w", "name": "Henry", "fans": 13, "review_count": 90, "average_stars": 3.84, "friends": [], "gender": "male", "age": 35}, {"user_id": "u-09QcQYf_t1NEq_AkjJuABA", "name": "Christina", "fans": 36, "review_count": 417, "average_stars": 4.12, "friends": [], "gender": "female", "age": 35}, {"user_id": "u-x8GuHHp7EJylrrq9HqL0fA", "name": "William", "fans": 0, "review_count": 25, "average_stars": 3.48, "friends": [], "gender": "male", "age": 56}, {"user_id": "u-BM6KnzoljE9t5qBrQjfdmQ", "name": "Melissa", "fans": 3, "review_count": 39, "average_stars": 3.74, "friends": ["u-WeHffRGwXVuqdQyOxsAg0Q"], "gender": "female", "age": 45}, {"user_id": "u-CapjGj9mWWL6P_eQChu-5g", "name": "Scott", "fans": 4, "review_count": 119, "average_stars": 3.42, "friends": [], "gender": "male", "age": 1}, {"user_id": "u-cfp7H2hRFCPsTdvMEkrbrQ", "name": "Courtney", "fans": 0, "review_count": 2, "average_stars": 4.0, "friends": [], "gender": "female", "age": 35}, {"user_id": "u-D34XpkChl5RnFlhFZvZFbg", "name": "Tony", "fans": 0, "review_count": 1, "average_stars": 5.0, "friends": [], "gender": "male", "age": 1}, {"user_id": "u-iyvmVqJAGF1UTh6HHKbQew", "name": "Lambeau", "fans": 0, "review_count": 21, "average_stars": 3.65, "friends": [], "gender": "female", "age": 35}, {"user_id": "u-fMcplBt_OQ7V-TQusZmTGw", "name": "C", "fans": 0, "review_count": 8, "average_stars": 3.63, "friends": [], "gender": "female", "age": 35}, {"user_id": "u-BdQOW8Nm6YNk7bk1wvr2Cg", "name": "Edward", "fans": 0, "review_count": 65, "average_stars": 3.17, "friends": [], "gender": "male", "age": 45}, {"user_id": "u-XqjeXUZ1BXzxl1HqLABX1w", "name": "Michael", "fans": 0, "review_count": 25, "average_stars": 3.93, "friends": [], "gender": "male", "age": 35}, {"user_id": "u-SalzPkE0sbOXF7erSlOKSQ", "name": "Kenneth", "fans": 0, "review_count": 21, "average_stars": 4.29, "friends": [], "gender": "male", "age": 35}, {"user_id": "u-J5eK0nDfQPlD0VeihS40kA", "name": "Kimberly", "fans": 0, "review_count": 17, "average_stars": 4.33, "friends": [], "gender": "female", "age": 25}, {"user_id": "u-cPKCbAf-XlMoGlDHLgPpYQ", "name": "Joel", "fans": 0, "review_count": 8, "average_stars": 3.25, "friends": [], "gender": "male", "age": 1}, {"user_id": "u-OnfwPAs_mVdSAEigKMFHQw", "name": "Katie", "fans": 1, "review_count": 29, "average_stars": 3.47, "friends": [], "gender": "female", "age": 25}, {"user_id": "u-M4P02bBbTauuwP6OhGpT-g", "name": "Aditi", "fans": 0, "review_count": 23, "average_stars": 3.38, "friends": [], "gender": "female", "age": 35}, {"user_id": "u-UG3JqmYlEWlNEOJqUMENDg", "name": "Aditi", "fans": 17, "review_count": 141, "average_stars": 3.98, "friends": [], "gender": "female", "age": 35}, {"user_id": "u-ZPz3QcLM9cBmS7znlLEb3Q", "name": "jim", "fans": 0, "review_count": 8, "average_stars": 4.0, "friends": [], "gender": "female", "age": 18}, {"user_id": "u-ORBwoRxcyxFtjNU5zuex_Q", "name": "Brooke", "fans": 0, "review_count": 1, "average_stars": 5.0, "friends": [], "gender": "female", "age": 45}, {"user_id": "u-bf2Twxnea_9NhIs-2lvK8g", "name": "Demi", "fans": 5, "review_count": 73, "average_stars": 3.27, "friends": [], "gender": "female", "age": 35}, {"user_id": "u-CgaxrZFHnfdXT8goelBTaA", "name": "Kelly", "fans": 2, "review_count": 53, "average_stars": 4.16, "friends": [], "gender": "female", "age": 1}, {"user_id": "u-I_wb3WV1EwwgH9i1ZrVkTw", "name": "Antoinette", "fans": 1, "review_count": 26, "average_stars": 4.54, "friends": [], "gender": "female", "age": 56}, {"user_id": "u-re6Tp9Q8nCKXOjggP8m1JA", "name": "Yvette", "fans": 0, "review_count": 3, "average_stars": 4.67, "friends": [], "gender": "female", "age": 18}, {"user_id": "u-oVThx4VpdF_IQjZRldcT6A", "name": "Matthew", "fans": 0, "review_count": 1, "average_stars": 5.0, "friends": [], "gender": "male", "age": 35}, {"user_id": "u-x8lutXxvDde5ZoHqfZzumg", "name": "Maddy", "fans": 0, "review_count": 1, "average_stars": 5.0, "friends": [], "gender": "female", "age": 25}, {"user_id": "u-eJ00Pm6BVn91jySR6ETCag", "name": "Chris", "fans": 1, "review_count": 77, "average_stars": 3.58, "friends": [], "gender": "male", "age": 25}, {"user_id": "u-Vlp4qA2_MRv9hQvJsA6kyg", "name": "Ania", "fans": 1, "review_count": 81, "average_stars": 3.99, "friends": [], "gender": "female", "age": 35}, {"user_id": "u-t0e6NZ9ssaSpJQnsD4GDmw", "name": "jon", "fans": 0, "review_count": 24, "average_stars": 3.83, "friends": [], "gender": "female", "age": 18}, {"user_id": "u-IbL4upXbKhB-puX6ffQlww", "name": "Megan", "fans": 0, "review_count": 15, "average_stars": 3.4, "friends": [], "gender": "female", "age": 35}, {"user_id": "u-WeHffRGwXVuqdQyOxsAg0Q", "name": "Emily", "fans": 21, "review_count": 170, "average_stars": 4.0, "friends": [], "gender": "female", "age": 35}, {"user_id": "u-hQ8zKPF90-hkLp_C_wYzsg", "name": "John", "fans": 0, "review_count": 71, "average_stars": 4.05, "friends": [], "gender": "male", "age": 35}, {"user_id": "u-mvIEbcSMGrX7h_Z_J6Jcgg", "name": "Pri", "fans": 0, "review_count": 10, "average_stars": 3.2, "friends": [], "gender": "female", "age": 25}, {"user_id": "u-nrUz27WKP4CCRaVhacp4jw", "name": "Jackie", "fans": 0, "review_count": 10, "average_stars": 4.69, "friends": [], "gender": "female", "age": 45}, {"user_id": "u-D3ubzB6RdOiMwJ6JFIL2Zw", "name": "Michael", "fans": 3, "review_count": 62, "average_stars": 3.82, "friends": [], "gender": "male", "age": 35}, {"user_id": "u-HazSV7hH9YrbDL6lOpS5Dg", "name": "Kelly", "fans": 0, "review_count": 5, "average_stars": 5.0, "friends": [], "gender": "female", "age": 25}, {"user_id": "u-94J1J7zJCVgfN8bz1qF-8g", "name": "Mohammed", "fans": 0, "review_count": 6, "average_stars": 3.5, "friends": [], "gender": "male", "age": 45}, {"user_id": "u-SKgQIHJVj7JU60kBKo8OZw", "name": "Matthew", "fans": 0, "review_count": 5, "average_stars": 4.2, "friends": [], "gender": "male", "age": 25}, {"user_id": "u-pI6jn3YCp2jSa8dH0FxZWg", "name": "D.", "fans": 0, "review_count": 4, "average_stars": 3.5, "friends": [], "gender": "female", "age": 35}, {"user_id": "u-kKsSDWIEMg9A9obAaY_NIw", "name": "Laura", "fans": 0, "review_count": 2, "average_stars": 3.67, "friends": [], "gender": "female", "age": 56}, {"user_id": "u-A_DdEIFJv5W-owkam1PSvw", "name": "Gurwinder", "fans": 0, "review_count": 3, "average_stars": 2.33, "friends": [], "gender": "male", "age": 25}, {"user_id": "u-brY1l1obnPNk-oyDcScyMw", "name": "Matthew", "fans": 0, "review_count": 2, "average_stars": 5.0, "friends": [], "gender": "male", "age": 18}, {"user_id": "u-cQrAV5NFK8vZ6qMiRLddVQ", "name": "Sarah", "fans": 0, "review_count": 10, "average_stars": 3.9, "friends": [], "gender": "female", "age": 35}, {"user_id": "u-pMf7ybLSBGrR7ABPzv2bag", "name": "M", "fans": 0, "review_count": 67, "average_stars": 3.18, "friends": [], "gender": "female", "age": 18}, {"user_id": "u-iEy2zChmzGTdv9n0t_jEPw", "name": "Jenee", "fans": 2, "review_count": 67, "average_stars": 4.18, "friends": [], "gender": "female", "age": 45}, {"user_id": "u-omMCW9cZNhmuue1sas2vFw", "name": "Adam", "fans": 0, "review_count": 4, "average_stars": 4.0, "friends": [], "gender": "male", "age": 45}, {"user_id": "u-MWtrV8O5NclWPrNvsxUVXg", "name": "Alex", "fans": 0, "review_count": 18, "average_stars": 4.5, "friends": [], "gender": "male", "age": 25}, {"user_id": "u-YqMpcRUA0OMw1WNLDGoj-A", "name": "Sue A.", "fans": 16, "review_count": 390, "average_stars": 3.05, "friends": [], "gender": "female", "age": 45}, {"user_id": "u-Nq6e5N8bjgD9B46O4va_zA", "name": "Sarah", "fans": 20, "review_count": 485, "average_stars": 3.88, "friends": [], "gender": "female", "age": 18}, {"user_id": "u-yRy06dgAS4CZ1eyE1bQ5QQ", "name": "Lia", "fans": 0, "review_count": 3, "average_stars": 3.33, "friends": [], "gender": "female", "age": 1}, {"user_id": "u-CxDOIDnH8gp9KXzpBHJYXw", "name": "Jennifer", "fans": 789, "review_count": 6633, "average_stars": 3.33, "friends": [], "gender": "female", "age": 25}, {"user_id": "u-GkSc8kWWbigUL_V5Q12GrA", "name": "Irina", "fans": 1, "review_count": 66, "average_stars": 4.19, "friends": [], "gender": "female", "age": 45}, {"user_id": "u-JSnZgpUfETfH8LcIYBP9Yg", "name": "Giselle", "fans": 10, "review_count": 177, "average_stars": 3.35, "friends": [], "gender": "female", "age": 35}, {"user_id": "u-Xmf0hrZ1S4zBcQ7GmidJ2Q", "name": "Jeff", "fans": 9, "review_count": 111, "average_stars": 4.1, "friends": [], "gender": "male", "age": 25}, {"user_id": "u-VUop7P6gVM95Ke2cHjX0Fg", "name": "Ryan", "fans": 1, "review_count": 102, "average_stars": 3.29, "friends": [], "gender": "male", "age": 45}, {"user_id": "u-ny-CJ25tLDl8_Oi7j-lbxw", "name": "Foodie", "fans": 0, "review_count": 36, "average_stars": 3.04, "friends": [], "gender": "female", "age": 35}, {"user_id": "u-rZwfucC2U81hGAGSceL5ew", "name": "Yusuf", "fans": 0, "review_count": 8, "average_stars": 2.33, "friends": [], "gender": "male", "age": 56}, {"user_id": "u-M9B4BJkv5ciSgkaUfif2Dw", "name": "Mamoun", "fans": 0, "review_count": 14, "average_stars": 2.36, "friends": [], "gender": "male", "age": 18}, {"user_id": "u-2U9yYe623iFuWICTIgDMQw", "name": "Sarah", "fans": 0, "review_count": 12, "average_stars": 3.42, "friends": [], "gender": "female", "age": 25}, {"user_id": "u-gesK7Oep93G_ViOFNiRjxQ", "name": "Yohanna", "fans": 1, "review_count": 14, "average_stars": 2.43, "friends": [], "gender": "male", "age": 1}, {"user_id": "u-Fjk3fN9-X5Hd1n5-pwoO0w", "name": "Ogan", "fans": 1, "review_count": 11, "average_stars": 4.18, "friends": [], "gender": "female", "age": 45}, {"user_id": "u-f1vwYzWxoF8OmOsidSiuuQ", "name": "Khalid", "fans": 0, "review_count": 34, "average_stars": 2.59, "friends": [], "gender": "male", "age": 45}, {"user_id": "u-qswybzqD9UD_my8fl0V7wQ", "name": "Ali", "fans": 0, "review_count": 30, "average_stars": 4.47, "friends": [], "gender": "male", "age": 45}, {"user_id": "u-1_cEjUy1_a2HUNp8_5oaGA", "name": "Silken", "fans": 2, "review_count": 6, "average_stars": 3.33, "friends": [], "gender": "female", "age": 35}, {"user_id": "u-cuB0D5lUemrEow1FOLv54Q", "name": "Ali", "fans": 0, "review_count": 20, "average_stars": 3.58, "friends": [], "gender": "male", "age": 18}, {"user_id": "u-fYUQbav_JlFe0U1WDxpA_w", "name": "Steven", "fans": 0, "review_count": 1, "average_stars": 1.0, "friends": [], "gender": "male", "age": 35}, {"user_id": "u-Yk3G57N4a3-k8edIKESrrA", "name": "Kalita", "fans": 0, "review_count": 4, "average_stars": 2.0, "friends": [], "gender": "male", "age": 45}, {"user_id": "u-liiY-jtE681B_fbP1sHfiw", "name": "Danial", "fans": 0, "review_count": 6, "average_stars": 4.67, "friends": ["u-ub8FMhBU6hJ0u1jjChlkyg"], "gender": "male", "age": 35}, {"user_id": "u-IdhiZofTvwWd_Ul5m338wQ", "name": "Abi", "fans": 7, "review_count": 59, "average_stars": 3.47, "friends": [], "gender": "female", "age": 25}, {"user_id": "u-R1eRQrEMvc5TKNOtU9Se1w", "name": "Calvin", "fans": 1, "review_count": 63, "average_stars": 3.22, "friends": [], "gender": "male", "age": 1}, {"user_id": "u-F9SQf5gkni1Ux4uTcqFQfg", "name": "Just", "fans": 0, "review_count": 3, "average_stars": 2.5, "friends": [], "gender": "male", "age": 25}, {"user_id": "u-DJTgCoGrU329Z5WZquX9KA", "name": "Bill", "fans": 0, "review_count": 24, "average_stars": 3.08, "friends": [], "gender": "male", "age": 45}, {"user_id": "u-ub8FMhBU6hJ0u1jjChlkyg", "name": "Agha", "fans": 2, "review_count": 7, "average_stars": 4.42, "friends": [], "gender": "male", "age": 56}, {"user_id": "u-SVyv-07pWaPySmY10oVZBA", "name": "Royston", "fans": 0, "review_count": 5, "average_stars": 3.4, "friends": [], "gender": "female", "age": 45}, {"user_id": "u-4LPsIyUQxuQAFOZOUqHvRQ", "name": "Ahad", "fans": 10, "review_count": 163, "average_stars": 3.49, "friends": [], "gender": "female", "age": 1}, {"user_id": "u-wWHeaOS28fnCnFN1Pmo3xg", "name": "Shaan", "fans": 7, "review_count": 234, "average_stars": 4.04, "friends": [], "gender": "female", "age": 1}, {"user_id": "u-bOS8YfYRt7Pa320yMRVNPQ", "name": "Sandra", "fans": 2, "review_count": 60, "average_stars": 3.03, "friends": [], "gender": "female", "age": 35}, {"user_id": "u-YgYlEhHXIa1O5NAy6SNS_g", "name": "Kelsey", "fans": 0, "review_count": 6, "average_stars": 3.43, "friends": [], "gender": "female", "age": 35}, {"user_id": "u-G2bIgYrIgdllZq4RT7ThRw", "name": "r", "fans": 0, "review_count": 6, "average_stars": 3.67, "friends": [], "gender": "female", "age": 18}, {"user_id": "u-8okt1nl-g2RL3ylWoqj4tA", "name": "K", "fans": 6, "review_count": 123, "average_stars": 3.81, "friends": [], "gender": "female", "age": 18}, {"user_id": "u-s2Od8Ty8glS4jHyLNGHgDQ", "name": "Ah", "fans": 7, "review_count": 109, "average_stars": 3.74, "friends": [], "gender": "female", "age": 35}, {"user_id": "u-CT9bcSQrpVLzml-CPKvzVQ", "name": "Malinda", "fans": 2, "review_count": 29, "average_stars": 3.81, "friends": [], "gender": "female", "age": 18}, {"user_id": "u-tLb-WQFc2fHo5MgF4DwSVw", "name": "Norman", "fans": 0, "review_count": 2, "average_stars": 4.5, "friends": [], "gender": "male", "age": 1}, {"user_id": "u-IZQhRicDrPQ3RWuHRUMM0Q", "name": "Frank", "fans": 2, "review_count": 66, "average_stars": 3.52, "friends": [], "gender": "male", "age": 25}, {"user_id": "u-ebDyKTggFXO7YfJmWyswRA", "name": "M", "fans": 0, "review_count": 6, "average_stars": 2.33, "friends": [], "gender": "female", "age": 25}, {"user_id": "u-XFoGm5ayOBBJqqSuiRuiFw", "name": "David", "fans": 1, "review_count": 50, "average_stars": 3.46, "friends": [], "gender": "male", "age": 25}, {"user_id": "u-FPmxLtMPlYDyeIa2f3N4qg", "name": "Dianne", "fans": 4, "review_count": 49, "average_stars": 4.02, "friends": [], "gender": "female", "age": 35}, {"user_id": "u-VV2NvlUq71E6QQya8tRbtQ", "name": "morgan", "fans": 0, "review_count": 2, "average_stars": 3.0, "friends": [], "gender": "female", "age": 35}, {"user_id": "u-ezW02HA5b_tIBZxN76wXOA", "name": "Steven", "fans": 1, "review_count": 55, "average_stars": 3.7, "friends": [], "gender": "male", "age": 35}, {"user_id": "u-8vfbA76TY8lR_7femAPtVw", "name": "Michelle", "fans": 1, "review_count": 11, "average_stars": 3.85, "friends": ["u-Bsbumyr3Of8BauN2URK4bg"], "gender": "female", "age": 56}, {"user_id": "u-ZvmC522FAwxt8qT1jxqliw", "name": "George", "fans": 11, "review_count": 267, "average_stars": 2.68, "friends": [], "gender": "male", "age": 45}, {"user_id": "u-HVq7SYfZ4hpFFVsAU_Ub_Q", "name": "Nikki", "fans": 8, "review_count": 86, "average_stars": 3.92, "friends": ["u-jfaz1aQqnkbtzQfQyCE8IA"], "gender": "female", "age": 35}, {"user_id": "u-jfaz1aQqnkbtzQfQyCE8IA", "name": "JJ", "fans": 50, "review_count": 243, "average_stars": 4.23, "friends": [], "gender": "female", "age": 45}, {"user_id": "u-aa505KhNCu9961nbTNTZAA", "name": "Tuul", "fans": 0, "review_count": 4, "average_stars": 3.25, "friends": [], "gender": "female", "age": 45}, {"user_id": "u-uPBdIJW1GrqBZ851BE_OZA", "name": "Angela", "fans": 2, "review_count": 33, "average_stars": 3.17, "friends": [], "gender": "female", "age": 18}, {"user_id": "u-Brp-xpqt3rqzeYaKgRNs1w", "name": "Marianela", "fans": 0, "review_count": 9, "average_stars": 4.64, "friends": [], "gender": "female", "age": 18}, {"user_id": "u-TB9ibgXVrq1B7-fajbsu8g", "name": "Giannabrie", "fans": 39, "review_count": 416, "average_stars": 3.58, "friends": [], "gender": "female", "age": 1}, {"user_id": "u-IQ3L56nvquTVJUB2xArJ_Q", "name": "E", "fans": 0, "review_count": 2, "average_stars": 5.0, "friends": [], "gender": "female", "age": 45}, {"user_id": "u-PvjiauDPX2IPz7ybrrFRFQ", "name": "J", "fans": 0, "review_count": 1, "average_stars": 4.0, "friends": [], "gender": "female", "age": 35}, {"user_id": "u-FoVZlbbz0e19YiOR8DCYLA", "name": "Susan", "fans": 33, "review_count": 851, "average_stars": 3.45, "friends": [], "gender": "female", "age": 35}, {"user_id": "u-JiRZzPhGTbcnzTpu-BsyEw", "name": "Sam", "fans": 8, "review_count": 187, "average_stars": 3.57, "friends": [], "gender": "male", "age": 18}, {"user_id": "u-3sY-Wj7CKDb9YjQm7LG5Ew", "name": "Sarah", "fans": 25, "review_count": 379, "average_stars": 3.65, "friends": [], "gender": "female", "age": 35}, {"user_id": "u-I2abmPzZK7pGDYD3LmNMkw", "name": "Andy", "fans": 0, "review_count": 2, "average_stars": 3.0, "friends": [], "gender": "male", "age": 45}, {"user_id": "u-nl5E0QN0oPLiGDGu_GbG4w", "name": "Jane", "fans": 0, "review_count": 14, "average_stars": 4.6, "friends": [], "gender": "female", "age": 56}, {"user_id": "u-c5BgNtehrBsJ45AAAJ67Gw", "name": "Simar", "fans": 1, "review_count": 12, "average_stars": 3.92, "friends": [], "gender": "female", "age": 18}, {"user_id": "u-xuZRkrpwxcnA4WnFIhmUGQ", "name": "Lissa", "fans": 0, "review_count": 2, "average_stars": 3.0, "friends": [], "gender": "female", "age": 25}, {"user_id": "u-_m92RQLYvNeaCm1Uk81eeA", "name": "Cara", "fans": 0, "review_count": 6, "average_stars": 4.17, "friends": [], "gender": "female", "age": 45}, {"user_id": "u-iqtM2OO8Ck6fAxcJ9jTgng", "name": "Shaminda", "fans": 0, "review_count": 70, "average_stars": 3.42, "friends": [], "gender": "female", "age": 18}, {"user_id": "u-8b8tlDCc2HE9G7rLEMF2lg", "name": "Long", "fans": 1, "review_count": 48, "average_stars": 3.53, "friends": [], "gender": "male", "age": 25}, {"user_id": "u-pMefTWo6gMdx8WhYSA2u3w", "name": "Bernie", "fans": 59, "review_count": 1132, "average_stars": 3.41, "friends": [], "gender": "female", "age": 35}, {"user_id": "u-1YZ-yIsbZVZ267ZLFT3s9w", "name": "A", "fans": 0, "review_count": 8, "average_stars": 2.5, "friends": [], "gender": "female", "age": 1}, {"user_id": "u-6ZCWi1OxWhooJkcrRnDs1w", "name": "Daryoosh", "fans": 0, "review_count": 1, "average_stars": 5.0, "friends": [], "gender": "male", "age": 45}, {"user_id": "u-zSl68XFwisQyr_TDXQj3ow", "name": "SandyMj", "fans": 11, "review_count": 108, "average_stars": 3.53, "friends": [], "gender": "female", "age": 18}, {"user_id": "u-_-dxjQHV1ubJ2CIvmQrHSg", "name": "Marty", "fans": 0, "review_count": 17, "average_stars": 4.0, "friends": [], "gender": "male", "age": 25}, {"user_id": "u-5xGEBRzywWVkG0IjWepqgQ", "name": "Fahad", "fans": 3, "review_count": 23, "average_stars": 4.03, "friends": [], "gender": "male", "age": 25}, {"user_id": "u-PzkA5dSmgKKtin7UZIGwsw", "name": "Zohaib", "fans": 1, "review_count": 42, "average_stars": 5.0, "friends": [], "gender": "female", "age": 18}, {"user_id": "u-fQNL5QkjjTSGmxJAC3xQmA", "name": "Andrea", "fans": 0, "review_count": 13, "average_stars": 4.5, "friends": [], "gender": "female", "age": 25}, {"user_id": "u-r8ifFR-vEmD-h9LdrR22Uw", "name": "Mehvish", "fans": 8, "review_count": 147, "average_stars": 3.41, "friends": [], "gender": "male", "age": 35}, {"user_id": "u-x3fvqMGdjCqhi-6UwOYbvQ", "name": "Shaji", "fans": 4, "review_count": 32, "average_stars": 4.15, "friends": [], "gender": "female", "age": 35}, {"user_id": "u-5zosNWWAHQrcWzsf-DIVXQ", "name": "Hirb", "fans": 0, "review_count": 6, "average_stars": 4.43, "friends": [], "gender": "female", "age": 25}, {"user_id": "u-uLEbum6dfeFm9jcpW73w1Q", "name": "Ayah", "fans": 7, "review_count": 71, "average_stars": 3.67, "friends": [], "gender": "female", "age": 56}, {"user_id": "u-9M9pCbQFCzFXltkEdGgqxw", "name": "Shabbir", "fans": 4, "review_count": 210, "average_stars": 4.23, "friends": [], "gender": "male", "age": 35}, {"user_id": "u-Y5jM9E19wy_x-Pxvs_eFhw", "name": "Charandeep", "fans": 4, "review_count": 61, "average_stars": 3.73, "friends": [], "gender": "female", "age": 25}, {"user_id": "u-45stHCps45t-AiIYo7kojg", "name": "Black", "fans": 0, "review_count": 24, "average_stars": 3.63, "friends": [], "gender": "female", "age": 18}, {"user_id": "u-NPPnwMFQjv80vV2mQr8tdg", "name": "Hungry", "fans": 0, "review_count": 174, "average_stars": 3.52, "friends": [], "gender": "female", "age": 35}, {"user_id": "u-wFc88erJk878O6SqJ1veAg", "name": "Jenn", "fans": 1, "review_count": 41, "average_stars": 4.19, "friends": [], "gender": "female", "age": 35}, {"user_id": "u-SRhUZfTNf_qis3x-1dSWnQ", "name": "Ibu", "fans": 0, "review_count": 3, "average_stars": 2.6, "friends": [], "gender": "female", "age": 18}, {"user_id": "u-HINrShGfauoae41fS8Y2hQ", "name": "Umairah", "fans": 0, "review_count": 7, "average_stars": 3.14, "friends": [], "gender": "female", "age": 18}, {"user_id": "u-oVLfMJMXgqZBe8sMXySYHA", "name": "Jawed", "fans": 0, "review_count": 3, "average_stars": 1.67, "friends": [], "gender": "male", "age": 25}, {"user_id": "u-XzjwALtc1m298JddEyiZWQ", "name": "Matthew", "fans": 0, "review_count": 5, "average_stars": 4.0, "friends": [], "gender": "male", "age": 18}, {"user_id": "u-3Fmj7MfGfsUUK1kTWCSL_g", "name": "Matthew", "fans": 6, "review_count": 42, "average_stars": 3.76, "friends": [], "gender": "male", "age": 45}, {"user_id": "u-B0Xxo-DtDejGVHQccS1iiA", "name": "Raina", "fans": 10, "review_count": 157, "average_stars": 3.31, "friends": [], "gender": "female", "age": 45}, {"user_id": "u-SRA86Xyf9fbOAhICWttMLQ", "name": "Eva", "fans": 5, "review_count": 141, "average_stars": 3.56, "friends": [], "gender": "female", "age": 1}, {"user_id": "u-LWu1oEhz4jhiV1o5K4amKA", "name": "'Hiraa", "fans": 0, "review_count": 2, "average_stars": 2.0, "friends": [], "gender": "female", "age": 25}, {"user_id": "u-8FYeHPf7b-itXR5zJqgjCw", "name": "Soubia", "fans": 0, "review_count": 1, "average_stars": 4.0, "friends": [], "gender": "female", "age": 18}, {"user_id": "u-e2RzU7qcX4bSo7lzlkPfog", "name": "Omar", "fans": 0, "review_count": 16, "average_stars": 3.35, "friends": [], "gender": "male", "age": 25}, {"user_id": "u-p9GBbKZXRk4Pici-quDB0A", "name": "Diana", "fans": 1, "review_count": 43, "average_stars": 3.3, "friends": [], "gender": "female", "age": 18}, {"user_id": "u-neiVdmFhXKTJhpnZzgLHPA", "name": "Sarra", "fans": 0, "review_count": 13, "average_stars": 3.46, "friends": [], "gender": "female", "age": 56}, {"user_id": "u-vsqpRyTbfNeAooBY_kecdw", "name": "Mahera", "fans": 0, "review_count": 2, "average_stars": 1.0, "friends": [], "gender": "female", "age": 18}, {"user_id": "u-qB6k6ubk1B6SkJYOWbdhSw", "name": "Sarita", "fans": 0, "review_count": 5, "average_stars": 3.6, "friends": [], "gender": "female", "age": 45}, {"user_id": "u-P8oZSufLPksOc7KoKGb1Vw", "name": "Chiqui", "fans": 6, "review_count": 66, "average_stars": 3.45, "friends": [], "gender": "male", "age": 56}, {"user_id": "u--1aYNZASC1lkA09LJtfNAA", "name": "Savio", "fans": 0, "review_count": 15, "average_stars": 3.76, "friends": [], "gender": "female", "age": 25}, {"user_id": "u-9tY4wJuJ5_HFW2CwfNoIIQ", "name": "H", "fans": 3, "review_count": 41, "average_stars": 3.61, "friends": [], "gender": "female", "age": 25}, {"user_id": "u-gDnR2a2N1vNNSEx1GgwtHA", "name": "Zhengchong", "fans": 3, "review_count": 49, "average_stars": 3.35, "friends": [], "gender": "female", "age": 35}, {"user_id": "u-oBzdBXQ5At99yK6kiIrjWA", "name": "Denise", "fans": 0, "review_count": 46, "average_stars": 4.59, "friends": [], "gender": "female", "age": 45}, {"user_id": "u-PLpm8j6lmu1tMhTR24O_pg", "name": "Ajay", "fans": 0, "review_count": 16, "average_stars": 3.59, "friends": [], "gender": "male", "age": 35}, {"user_id": "u-npdzLLzPtB9FIUXlfpeUCQ", "name": "NY", "fans": 1, "review_count": 52, "average_stars": 2.69, "friends": [], "gender": "female", "age": 35}, {"user_id": "u-rVsu1V6P7pJom8eJbE9tow", "name": "Ruby", "fans": 0, "review_count": 51, "average_stars": 3.06, "friends": [], "gender": "female", "age": 45}, {"user_id": "u-RypxyWecy2gbECH3-yU4eA", "name": "Nam", "fans": 5, "review_count": 104, "average_stars": 3.71, "friends": [], "gender": "male", "age": 56}, {"user_id": "u-ByQUXmVgJW6jNOzPgweW4g", "name": "Sam", "fans": 0, "review_count": 1, "average_stars": 1.0, "friends": ["u-jnB_saJqNfOmVoCWquhAzg"], "gender": "male", "age": 1}, {"user_id": "u-6n54T9Gr-wleIdzdN1QIxw", "name": "Aaisha", "fans": 0, "review_count": 2, "average_stars": 4.5, "friends": [], "gender": "male", "age": 1}, {"user_id": "u-Erw46-4d-QIzmj1ULQE0YA", "name": "David", "fans": 23, "review_count": 230, "average_stars": 3.98, "friends": [], "gender": "male", "age": 25}, {"user_id": "u-9fgBA8JsS1RZTCShEGj-xg", "name": "V", "fans": 0, "review_count": 9, "average_stars": 4.56, "friends": [], "gender": "female", "age": 35}, {"user_id": "u-SUyFqtj7G2hXLVKlRjvgCw", "name": "Ben", "fans": 1, "review_count": 43, "average_stars": 3.09, "friends": [], "gender": "male", "age": 45}, {"user_id": "u-wXgrBZo17Ku26EhsseCvyw", "name": "Priya", "fans": 0, "review_count": 7, "average_stars": 1.44, "friends": [], "gender": "female", "age": 35}, {"user_id": "u-1R_hou5lgjLWsZmYHOSCnQ", "name": "Kunal", "fans": 0, "review_count": 1, "average_stars": 1.0, "friends": [], "gender": "female", "age": 25}, {"user_id": "u-WxnV04J-4oIh_JzbPSCplg", "name": "Filbert", "fans": 0, "review_count": 4, "average_stars": 2.0, "friends": [], "gender": "female", "age": 45}, {"user_id": "u-8vByLahzAsULpdXqF3wQPA", "name": "Sajeethan", "fans": 0, "review_count": 4, "average_stars": 1.25, "friends": [], "gender": "female", "age": 25}, {"user_id": "u-gUlG-5PuBegHXQpk3E-pwA", "name": "Verinder", "fans": 0, "review_count": 2, "average_stars": 3.0, "friends": [], "gender": "female", "age": 25}, {"user_id": "u-mkG5CBX5zbvKLOhHBaaYFg", "name": "Ranger", "fans": 0, "review_count": 5, "average_stars": 4.2, "friends": [], "gender": "male", "age": 45}, {"user_id": "u-It-sLq9NQMIl9tqdY31Tyg", "name": "Princess", "fans": 0, "review_count": 6, "average_stars": 2.5, "friends": [], "gender": "female", "age": 45}, {"user_id": "u-UFl-AzsPSBvXj5XV682mEg", "name": "Sarah", "fans": 0, "review_count": 1, "average_stars": 1.0, "friends": [], "gender": "female", "age": 25}, {"user_id": "u-43gQxtscCBxJGcYfnBIPuw", "name": "Mohit", "fans": 0, "review_count": 1, "average_stars": 2.0, "friends": [], "gender": "female", "age": 18}, {"user_id": "u-aw1Qv3h6DkkaFka3xy-lWw", "name": "Zeynep", "fans": 0, "review_count": 8, "average_stars": 2.13, "friends": [], "gender": "female", "age": 1}, {"user_id": "u-lxLvaKzRcN-7gtxyywgRbA", "name": "Hina", "fans": 29, "review_count": 462, "average_stars": 3.64, "friends": [], "gender": "female", "age": 25}, {"user_id": "u-XkCwqx1moKGJFYNozHLUiw", "name": "Danielle", "fans": 0, "review_count": 1, "average_stars": 1.0, "friends": [], "gender": "female", "age": 56}, {"user_id": "u-ktrb5N_Ue8Ffmu_36dhTog", "name": "Leon", "fans": 0, "review_count": 5, "average_stars": 2.8, "friends": [], "gender": "male", "age": 25}, {"user_id": "u-SNEQ38uURxKjkBDheJ5zYw", "name": "Rita", "fans": 0, "review_count": 4, "average_stars": 3.0, "friends": [], "gender": "female", "age": 45}, {"user_id": "u-OqdJYU9BZ8bxOtuzX96IAw", "name": "Aditi", "fans": 0, "review_count": 49, "average_stars": 3.96, "friends": [], "gender": "female", "age": 56}, {"user_id": "u-jYDa14HsvZnY0C3pulotYA", "name": "Bibhuti", "fans": 0, "review_count": 18, "average_stars": 3.89, "friends": [], "gender": "female", "age": 56}, {"user_id": "u-j6YHy5kkqMy2yG-z6E6CqQ", "name": "Uday", "fans": 0, "review_count": 1, "average_stars": 1.0, "friends": [], "gender": "male", "age": 25}, {"user_id": "u-jlMfpKtkqXn_cLgylIrMeA", "name": "Rohit", "fans": 0, "review_count": 6, "average_stars": 2.0, "friends": [], "gender": "female", "age": 25}, {"user_id": "u-Ev5Ggic5S85xKgD4rglyWw", "name": "Kartik", "fans": 0, "review_count": 48, "average_stars": 3.9, "friends": [], "gender": "female", "age": 35}, {"user_id": "u-oif4M6LGAnXulFQVI6PH3A", "name": "Jane", "fans": 0, "review_count": 3, "average_stars": 1.0, "friends": [], "gender": "female", "age": 25}, {"user_id": "u-elLLVX0sGDlRrJsKJSDb3A", "name": "Shane", "fans": 0, "review_count": 9, "average_stars": 4.67, "friends": [], "gender": "male", "age": 25}, {"user_id": "u-Xx54oACO47neDL0vVMNNIQ", "name": "Mohana", "fans": 0, "review_count": 4, "average_stars": 5.0, "friends": [], "gender": "female", "age": 56}, {"user_id": "u-MavSq5J2vsW5qoteLa0DFg", "name": "Prads", "fans": 0, "review_count": 4, "average_stars": 2.75, "friends": [], "gender": "female", "age": 45}, {"user_id": "u-MW2pHbbkYIh92CWfpi6q1g", "name": "Sridhar", "fans": 0, "review_count": 9, "average_stars": 3.9, "friends": [], "gender": "female", "age": 25}, {"user_id": "u-x5WjZ3PkPbG6X4LFueFFiQ", "name": "J", "fans": 0, "review_count": 5, "average_stars": 5.0, "friends": [], "gender": "female", "age": 56}, {"user_id": "u-H3KluKXf1mp3etCToCJhqg", "name": "Mike", "fans": 15, "review_count": 450, "average_stars": 4.43, "friends": [], "gender": "male", "age": 45}, {"user_id": "u-koN3P_Emyd0wba8fHW3y5Q", "name": "beth", "fans": 0, "review_count": 14, "average_stars": 4.44, "friends": [], "gender": "female", "age": 25}, {"user_id": "u-tLD-WMe6PHmb81IeP1deWA", "name": "Sreedevi", "fans": 0, "review_count": 1, "average_stars": 5.0, "friends": [], "gender": "male", "age": 56}, {"user_id": "u-fOM--lHTt5ZIe0KivRHH6A", "name": "Jai Kiran", "fans": 0, "review_count": 1, "average_stars": 4.0, "friends": [], "gender": "male", "age": 18}, {"user_id": "u-NwQKDekLl0ttb7KuBZdUlw", "name": "Chris", "fans": 0, "review_count": 91, "average_stars": 2.96, "friends": [], "gender": "male", "age": 35}, {"user_id": "u-pAungxFZuZH5zd6SoD6RNg", "name": "Brita", "fans": 0, "review_count": 49, "average_stars": 3.43, "friends": [], "gender": "female", "age": 25}, {"user_id": "u-Hf0J8ocx_-N9jvqYEAQrsg", "name": "Bhairy", "fans": 0, "review_count": 4, "average_stars": 3.25, "friends": [], "gender": "female", "age": 35}, {"user_id": "u-GCIFapvuzWYMJunSjA5b_Q", "name": "L", "fans": 0, "review_count": 22, "average_stars": 4.77, "friends": [], "gender": "female", "age": 25}, {"user_id": "u-nV-0o4NVrcOtIY4w_t32LA", "name": "Bhaskar", "fans": 0, "review_count": 1, "average_stars": 1.0, "friends": [], "gender": "male", "age": 35}, {"user_id": "u-3veFPGLWvvEgzD2ut7rFFA", "name": "Jim", "fans": 0, "review_count": 26, "average_stars": 4.11, "friends": [], "gender": "male", "age": 1}, {"user_id": "u-_4YSlCbm-WHGbmut-FCeuw", "name": "Rod", "fans": 0, "review_count": 3, "average_stars": 3.33, "friends": [], "gender": "male", "age": 18}, {"user_id": "u-GxaSl-OEmnmTZ5AxC5S8Tg", "name": "Reddy", "fans": 0, "review_count": 2, "average_stars": 5.0, "friends": [], "gender": "female", "age": 35}, {"user_id": "u-Rc_53_nG895CxygTRRuDmw", "name": "N", "fans": 0, "review_count": 8, "average_stars": 2.18, "friends": [], "gender": "female", "age": 56}, {"user_id": "u-H9Tx30KywPKp9E--NqnBdg", "name": "Ravindra", "fans": 0, "review_count": 1, "average_stars": 5.0, "friends": [], "gender": "female", "age": 25}, {"user_id": "u-buuYBnht4326LLPzJjnAyw", "name": "April", "fans": 0, "review_count": 2, "average_stars": 1.0, "friends": [], "gender": "female", "age": 18}, {"user_id": "u-rvRpfdMe-mPEKDHcaxRu2g", "name": "Hungry", "fans": 0, "review_count": 37, "average_stars": 4.0, "friends": [], "gender": "female", "age": 56}, {"user_id": "u-lale6wOwUvQE15413NKUaw", "name": "Mansi", "fans": 0, "review_count": 16, "average_stars": 2.76, "friends": [], "gender": "male", "age": 25}, {"user_id": "u-_pjGXXo-g41vhDIIyjy7Fg", "name": "Michellin", "fans": 0, "review_count": 41, "average_stars": 3.6, "friends": [], "gender": "female", "age": 1}, {"user_id": "u-GCnB1Qs2wNur4B3_ih-1Iw", "name": "Thulasi", "fans": 0, "review_count": 16, "average_stars": 4.63, "friends": [], "gender": "female", "age": 35}, {"user_id": "u-PzjAqkfNN9olT1I7-EGZbA", "name": "Rabia", "fans": 0, "review_count": 3, "average_stars": 5.0, "friends": [], "gender": "female", "age": 56}, {"user_id": "u-aypH7RlO7B0mXngTXXhFNA", "name": "Pavan", "fans": 0, "review_count": 2, "average_stars": 4.5, "friends": [], "gender": "female", "age": 35}, {"user_id": "u-i_FXWLldE2DKgvE8dXwp2A", "name": "Anjana", "fans": 0, "review_count": 12, "average_stars": 3.75, "friends": [], "gender": "female", "age": 35}, {"user_id": "u-Icl6FPyBNFm6VREuL32XEA", "name": "Akshaya", "fans": 10, "review_count": 77, "average_stars": 3.94, "friends": [], "gender": "male", "age": 25}, {"user_id": "u-9TC7-M_iaH9Xg4c4CjhetA", "name": "Jennifer", "fans": 5, "review_count": 242, "average_stars": 3.99, "friends": [], "gender": "female", "age": 45}, {"user_id": "u-QGop4dOKhnBZ-LHhc5yqPA", "name": "Prabhu", "fans": 0, "review_count": 5, "average_stars": 3.4, "friends": [], "gender": "male", "age": 25}, {"user_id": "u-m35ODBrr76JYr20nxoMg_w", "name": "The", "fans": 16, "review_count": 584, "average_stars": 2.74, "friends": [], "gender": "female", "age": 45}, {"user_id": "u-mVvYiiWhZoVVhH_-Y-H85g", "name": "Brandi", "fans": 0, "review_count": 36, "average_stars": 3.5, "friends": [], "gender": "female", "age": 25}, {"user_id": "u-4oTUo9_a4pxKstYc6aV8FA", "name": "Sujith", "fans": 0, "review_count": 24, "average_stars": 3.14, "friends": [], "gender": "female", "age": 25}, {"user_id": "u-TB-Uy3latKcMg2TrVhcvJQ", "name": "Tony", "fans": 0, "review_count": 13, "average_stars": 1.0, "friends": [], "gender": "male", "age": 35}, {"user_id": "u-6gQIyHGFww47hQvd83_mBQ", "name": "Deepika", "fans": 0, "review_count": 7, "average_stars": 3.71, "friends": [], "gender": "female", "age": 45}, {"user_id": "u-PcbsVShGWMQ0vi-SAHtrQw", "name": "Raghu", "fans": 0, "review_count": 7, "average_stars": 4.0, "friends": [], "gender": "female", "age": 35}, {"user_id": "u-KNE0o7pq_GEvog0tNr7-qA", "name": "Pete", "fans": 3, "review_count": 35, "average_stars": 4.31, "friends": [], "gender": "male", "age": 56}, {"user_id": "u-1dWKT_QG9yvMVBuoDGhavQ", "name": "James", "fans": 0, "review_count": 8, "average_stars": 3.55, "friends": [], "gender": "male", "age": 35}, {"user_id": "u-RWLGf8awicP4AUtUj9760g", "name": "Joseph", "fans": 0, "review_count": 9, "average_stars": 1.56, "friends": [], "gender": "male", "age": 56}, {"user_id": "u-XMzGoWjs1-O3747rKLDdDg", "name": "\u306b\u3057\u30fc", "fans": 0, "review_count": 3, "average_stars": 3.0, "friends": [], "gender": "female", "age": 18}, {"user_id": "u-P6rpdRwuwC9cTgaNnU1JaA", "name": "Taerra", "fans": 10, "review_count": 129, "average_stars": 4.19, "friends": [], "gender": "female", "age": 18}, {"user_id": "u-DxphAmMcFnCXq5hW4tRnuA", "name": "Zafina", "fans": 0, "review_count": 4, "average_stars": 3.5, "friends": [], "gender": "female", "age": 18}, {"user_id": "u-mK_kHEUabQJW5oOJwdOvmQ", "name": "Jacob", "fans": 0, "review_count": 4, "average_stars": 5.0, "friends": [], "gender": "male", "age": 35}, {"user_id": "u-xYH2WNVI7qc8RwBKJYh2Pg", "name": "Seshini", "fans": 0, "review_count": 2, "average_stars": 3.0, "friends": [], "gender": "male", "age": 1}, {"user_id": "u-sfzUgKqNupckAeDywfdedA", "name": "Helen", "fans": 0, "review_count": 9, "average_stars": 4.67, "friends": [], "gender": "female", "age": 18}, {"user_id": "u-b995vw7UKtFXdtI_ZmlzMQ", "name": "LA", "fans": 1, "review_count": 60, "average_stars": 3.64, "friends": [], "gender": "female", "age": 45}, {"user_id": "u-1mM1SMzqdHxucYUIUFisNw", "name": "Mika", "fans": 0, "review_count": 25, "average_stars": 3.6, "friends": [], "gender": "male", "age": 35}, {"user_id": "u-pDAkN1bGqHjpyXy-l0CoAg", "name": "Carol", "fans": 0, "review_count": 1, "average_stars": 5.0, "friends": [], "gender": "female", "age": 56}, {"user_id": "u-HdfsPpF9UVsGUrsgp6jYpw", "name": "David", "fans": 0, "review_count": 14, "average_stars": 2.21, "friends": [], "gender": "male", "age": 25}, {"user_id": "u-x5c57CXCNqqENGy9LAdGnA", "name": "Robyn", "fans": 1, "review_count": 92, "average_stars": 2.93, "friends": [], "gender": "female", "age": 25}, {"user_id": "u-W2mSXNvEt2xtuFZaGKFEww", "name": "Gautam", "fans": 0, "review_count": 12, "average_stars": 3.93, "friends": [], "gender": "male", "age": 35}, {"user_id": "u-VbB0_jzI_DrnPY4DuROVkQ", "name": "Bruce", "fans": 4, "review_count": 260, "average_stars": 3.2, "friends": [], "gender": "male", "age": 56}, {"user_id": "u-e4kh1V40FNlfsvMrqRvKdw", "name": "Jenn", "fans": 0, "review_count": 6, "average_stars": 4.67, "friends": [], "gender": "female", "age": 45}, {"user_id": "u-7ly3al1MaAOoUXUo2w9gIw", "name": "Maria", "fans": 0, "review_count": 2, "average_stars": 3.5, "friends": [], "gender": "female", "age": 25}, {"user_id": "u-wgkjjTkyLPXBq_JW3N-Zkw", "name": "Kristi", "fans": 6, "review_count": 231, "average_stars": 3.89, "friends": [], "gender": "female", "age": 56}, {"user_id": "u-WWhhLPW1_qdyZQsUqttfwQ", "name": "Daniel", "fans": 0, "review_count": 10, "average_stars": 2.8, "friends": [], "gender": "male", "age": 35}, {"user_id": "u-il4pARn-6muHdOneCf-4BA", "name": "Rajanandhini", "fans": 0, "review_count": 26, "average_stars": 3.27, "friends": [], "gender": "male", "age": 25}, {"user_id": "u-x_bHnIh87kEXYLh0T8u-aw", "name": "Utsav", "fans": 1, "review_count": 37, "average_stars": 3.68, "friends": [], "gender": "female", "age": 25}, {"user_id": "u-tjTrsF-CpDnTcclX-3sCTw", "name": "Al", "fans": 44, "review_count": 859, "average_stars": 3.19, "friends": [], "gender": "male", "age": 45}, {"user_id": "u-_LpeXjhiuMUvRo5QZtc90A", "name": "Santie", "fans": 0, "review_count": 4, "average_stars": 4.75, "friends": ["u-tjTrsF-CpDnTcclX-3sCTw"], "gender": "female", "age": 35}, {"user_id": "u-tRmW0n2d_Q4c_TXqfUSINA", "name": "Ed", "fans": 7, "review_count": 290, "average_stars": 3.55, "friends": [], "gender": "male", "age": 35}, {"user_id": "u-ON_4MwqybgZx3cq4ZoNlXQ", "name": "Kent", "fans": 0, "review_count": 4, "average_stars": 3.75, "friends": [], "gender": "male", "age": 35}, {"user_id": "u-QozLnf7sjzQ0IRzEAsepKQ", "name": "Karen", "fans": 3, "review_count": 60, "average_stars": 3.29, "friends": [], "gender": "female", "age": 35}, {"user_id": "u-qOdmye8UQdqloVNE059PkQ", "name": "Robin", "fans": 10, "review_count": 295, "average_stars": 3.53, "friends": [], "gender": "male", "age": 56}, {"user_id": "u-Kf10dTiGlcnyhj8DBoZn1A", "name": "Nav", "fans": 5, "review_count": 146, "average_stars": 3.32, "friends": [], "gender": "female", "age": 25}, {"user_id": "u-KpAsepiCArojuvCOt3Psvg", "name": "Andrew", "fans": 0, "review_count": 5, "average_stars": 2.6, "friends": [], "gender": "male", "age": 35}, {"user_id": "u-cPkxd2kmynEMTvLzEoGCvA", "name": "Alison", "fans": 1, "review_count": 15, "average_stars": 3.95, "friends": [], "gender": "female", "age": 25}, {"user_id": "u-TRBCyBaHTwWim71gizj2VQ", "name": "Christina", "fans": 0, "review_count": 7, "average_stars": 4.14, "friends": [], "gender": "female", "age": 35}, {"user_id": "u-1JWELY2_qH34RiIU39W3fg", "name": "Darby", "fans": 0, "review_count": 4, "average_stars": 4.75, "friends": [], "gender": "female", "age": 45}, {"user_id": "u-Scrk0HIe3GClR57Bq-Ud4A", "name": "Laura", "fans": 1, "review_count": 8, "average_stars": 3.75, "friends": [], "gender": "female", "age": 45}, {"user_id": "u-qCYSdhsOzHBKT-V72BiYNA", "name": "Suor", "fans": 32, "review_count": 637, "average_stars": 3.77, "friends": [], "gender": "female", "age": 18}, {"user_id": "u-cXQyz5jyV0ANMxMY9QILJA", "name": "Lisa", "fans": 0, "review_count": 1, "average_stars": 1.0, "friends": [], "gender": "female", "age": 35}, {"user_id": "u-6BvOG5QZswX4l0IbicFFIQ", "name": "Shon", "fans": 1, "review_count": 14, "average_stars": 4.6, "friends": [], "gender": "male", "age": 18}, {"user_id": "u-Z2dm8tS48n2jM8adDiLwiA", "name": "Annett", "fans": 0, "review_count": 40, "average_stars": 3.7, "friends": [], "gender": "female", "age": 45}, {"user_id": "u-UHHraFRu5NKvZqIHp2O02w", "name": "Robin", "fans": 2, "review_count": 209, "average_stars": 4.0, "friends": [], "gender": "male", "age": 45}, {"user_id": "u-LyjEBN-9r5BLStzwBgIfXg", "name": "ChristianChristopher", "fans": 0, "review_count": 50, "average_stars": 3.74, "friends": [], "gender": "female", "age": 45}, {"user_id": "u-Ai_edjBlEUalvELH00ADqQ", "name": "Mark", "fans": 0, "review_count": 11, "average_stars": 4.45, "friends": [], "gender": "male", "age": 35}, {"user_id": "u-avDs3nH7aOJWLevEJqX4Qw", "name": "JP", "fans": 1, "review_count": 24, "average_stars": 3.96, "friends": [], "gender": "female", "age": 35}, {"user_id": "u-S2pt8jKF_SKXAOeB8ESdXA", "name": "Maria", "fans": 1, "review_count": 37, "average_stars": 3.79, "friends": [], "gender": "female", "age": 18}, {"user_id": "u-Ug5HkPvMuvIMN8CSGPG30w", "name": "Ann", "fans": 0, "review_count": 16, "average_stars": 3.58, "friends": [], "gender": "female", "age": 25}, {"user_id": "u-8BJ4VEi11-XN8a-rqjo3Qg", "name": "Saul", "fans": 0, "review_count": 8, "average_stars": 4.0, "friends": [], "gender": "male", "age": 35}, {"user_id": "u-Nx4R_BdL5nspyQOgG3VwUQ", "name": "Warren", "fans": 0, "review_count": 67, "average_stars": 3.96, "friends": [], "gender": "male", "age": 56}, {"user_id": "u-mIDzFVnP2QnAh6ReQ9Imfg", "name": "Philip", "fans": 0, "review_count": 23, "average_stars": 2.87, "friends": [], "gender": "male", "age": 18}, {"user_id": "u-PPSljqrvJ1AuIp4mi12qAg", "name": "Kristine", "fans": 0, "review_count": 1, "average_stars": 5.0, "friends": [], "gender": "female", "age": 45}, {"user_id": "u-D3fOi-5w4intrUTWXzIQew", "name": "Moses", "fans": 35, "review_count": 610, "average_stars": 3.89, "friends": [], "gender": "male", "age": 18}, {"user_id": "u-eIs903qIpxuYvKM2Kmas-A", "name": "Dione", "fans": 12, "review_count": 93, "average_stars": 4.26, "friends": [], "gender": "female", "age": 18}, {"user_id": "u-F85Fe16McFDJFK0vnLy7Iw", "name": "Blake", "fans": 5, "review_count": 320, "average_stars": 4.14, "friends": [], "gender": "male", "age": 1}, {"user_id": "u-vuwSLU49A-NgW9S5uAvJxw", "name": "702", "fans": 1, "review_count": 59, "average_stars": 2.91, "friends": [], "gender": "female", "age": 35}, {"user_id": "u-Hiz0uGK0JB-xdAuTjrDIlg", "name": "Austine", "fans": 1, "review_count": 8, "average_stars": 4.75, "friends": [], "gender": "female", "age": 18}, {"user_id": "u-qnGoa8IzV16nV93NOvXhIA", "name": "Gil", "fans": 1, "review_count": 16, "average_stars": 4.0, "friends": [], "gender": "male", "age": 18}, {"user_id": "u-Rx-lnDQMrVgqnI0Pcb2Q5w", "name": "Alvaro", "fans": 2, "review_count": 31, "average_stars": 4.34, "friends": [], "gender": "male", "age": 25}, {"user_id": "u-wZ_Re2rPJ6vQAOkV2TqLmA", "name": "Melissa", "fans": 0, "review_count": 16, "average_stars": 4.65, "friends": [], "gender": "female", "age": 18}, {"user_id": "u-WuvSmp8UhNrPUFnB5gm-kg", "name": "David", "fans": 0, "review_count": 39, "average_stars": 3.6, "friends": [], "gender": "male", "age": 56}, {"user_id": "u-ylku-3TJU62S1mnKlxDDtA", "name": "Omar", "fans": 1, "review_count": 13, "average_stars": 4.71, "friends": [], "gender": "male", "age": 18}, {"user_id": "u-l9zbub5CchE3fCOPMz34Cw", "name": "Theresa", "fans": 0, "review_count": 39, "average_stars": 3.79, "friends": [], "gender": "female", "age": 45}, {"user_id": "u-pXZu2slCZS3BbFyG_UCG5Q", "name": "Alyssa", "fans": 1, "review_count": 22, "average_stars": 3.38, "friends": [], "gender": "female", "age": 35}, {"user_id": "u-pMsdsACQEp24fnpE3bur9A", "name": "Jillian", "fans": 0, "review_count": 6, "average_stars": 4.33, "friends": [], "gender": "female", "age": 1}, {"user_id": "u-FuDerME3t0XjuaPTrNfW_g", "name": "Janice", "fans": 0, "review_count": 7, "average_stars": 4.6, "friends": [], "gender": "female", "age": 35}, {"user_id": "u-jJCPbzLsomuw--fsWRJKVA", "name": "Priyanka", "fans": 0, "review_count": 2, "average_stars": 5.0, "friends": [], "gender": "female", "age": 45}, {"user_id": "u-p8CJMoVYzYMz9JkHomErAg", "name": "Manuel", "fans": 0, "review_count": 3, "average_stars": 5.0, "friends": [], "gender": "male", "age": 56}, {"user_id": "u-4T0cBpmbAaMJu5d5WNuQtg", "name": "Cynthia", "fans": 0, "review_count": 12, "average_stars": 4.15, "friends": [], "gender": "female", "age": 35}, {"user_id": "u-4V6vZgVCfEfYwXFK3tnTQQ", "name": "Jamie", "fans": 4, "review_count": 153, "average_stars": 4.27, "friends": [], "gender": "female", "age": 1}, {"user_id": "u--RA9NLalwmRTOX_8UMHnVQ", "name": "Lotus", "fans": 11, "review_count": 93, "average_stars": 4.17, "friends": [], "gender": "female", "age": 56}, {"user_id": "u-K3hhXg0HMZV2S2oySuvHfg", "name": "Charleston", "fans": 0, "review_count": 2, "average_stars": 5.0, "friends": [], "gender": "female", "age": 1}, {"user_id": "u-BynpqTILMY4OLLG9PgrKzQ", "name": "mike", "fans": 1, "review_count": 98, "average_stars": 2.5, "friends": [], "gender": "female", "age": 1}, {"user_id": "u-gtuRablOmw5O08QoKbn0fQ", "name": "Dustin", "fans": 29, "review_count": 463, "average_stars": 4.18, "friends": [], "gender": "male", "age": 35}, {"user_id": "u-snMnFg2KebIxkhcVHJ8r-w", "name": "Rudy", "fans": 0, "review_count": 29, "average_stars": 4.84, "friends": [], "gender": "male", "age": 56}, {"user_id": "u-70y3kxLziMsg8XyrVzwktQ", "name": "Ricardo", "fans": 0, "review_count": 10, "average_stars": 4.09, "friends": [], "gender": "male", "age": 45}, {"user_id": "u-9W8yd-mOS3dPGrpY_ryAng", "name": "John", "fans": 0, "review_count": 2, "average_stars": 3.0, "friends": [], "gender": "male", "age": 35}, {"user_id": "u-Y-sW-k-vT3jXCfYoOZLt5w", "name": "April", "fans": 2, "review_count": 17, "average_stars": 3.53, "friends": [], "gender": "female", "age": 25}, {"user_id": "u-UCG-PGg-rI8DdxbO9-SDyA", "name": "Darren", "fans": 17, "review_count": 15, "average_stars": 2.31, "friends": [], "gender": "male", "age": 35}, {"user_id": "u-ehAvwDt4Fpsz9KPordu5lA", "name": "Chris", "fans": 3, "review_count": 186, "average_stars": 3.88, "friends": [], "gender": "male", "age": 56}, {"user_id": "u-yotSLy34qVfBbMzU-goVWQ", "name": "Dena", "fans": 0, "review_count": 22, "average_stars": 4.32, "friends": [], "gender": "female", "age": 35}, {"user_id": "u-OWwO6rlPLSINNYA4RNCToA", "name": "Kailey", "fans": 1, "review_count": 16, "average_stars": 4.0, "friends": [], "gender": "female", "age": 35}, {"user_id": "u-4XumCjcCk9sHVfXXTsHzcw", "name": "Anthony", "fans": 0, "review_count": 5, "average_stars": 4.17, "friends": [], "gender": "male", "age": 18}, {"user_id": "u-JtAoso0Ze87DWqnmI5qorA", "name": "Troi", "fans": 20, "review_count": 89, "average_stars": 3.61, "friends": [], "gender": "female", "age": 56}, {"user_id": "u-NpzLHUDwsVnciPdialPolg", "name": "Hello", "fans": 0, "review_count": 5, "average_stars": 2.8, "friends": [], "gender": "female", "age": 35}, {"user_id": "u-e0KcqeKhCnwL1UZRGLv6_Q", "name": "Joseph", "fans": 0, "review_count": 8, "average_stars": 3.8, "friends": [], "gender": "male", "age": 45}, {"user_id": "u-PKEzKWv_FktMm2mGPjwd0Q", "name": "Norm", "fans": 319, "review_count": 2570, "average_stars": 3.75, "friends": [], "gender": "female", "age": 25}, {"user_id": "u-NTWjKabDCS5KBryITdV72A", "name": "Harout", "fans": 0, "review_count": 14, "average_stars": 3.57, "friends": [], "gender": "female", "age": 35}, {"user_id": "u-bpgbVPJcG-wQ4cNBcPPIxw", "name": "Monica", "fans": 227, "review_count": 1113, "average_stars": 4.11, "friends": [], "gender": "female", "age": 35}, {"user_id": "u-fH1TpgVyMuQcColrknmbZA", "name": "Rebecca", "fans": 0, "review_count": 32, "average_stars": 3.24, "friends": [], "gender": "female", "age": 35}, {"user_id": "u-nie-JYFTdUp04tlH527SDQ", "name": "Ren", "fans": 1, "review_count": 76, "average_stars": 3.21, "friends": [], "gender": "female", "age": 1}, {"user_id": "u-q6eks8g-8ve1AXMh1MTKJA", "name": "J A", "fans": 3, "review_count": 100, "average_stars": 3.23, "friends": [], "gender": "female", "age": 35}, {"user_id": "u-79uQM6mAgJJcmYRtMO_u1Q", "name": "Jeff", "fans": 5, "review_count": 175, "average_stars": 2.87, "friends": [], "gender": "male", "age": 25}, {"user_id": "u-SzcrUoOdo5LSy98sIgj0lA", "name": "Kent", "fans": 0, "review_count": 3, "average_stars": 3.33, "friends": [], "gender": "male", "age": 25}, {"user_id": "u-gCp21sfvL6HnQOvapeV7sw", "name": "Frank", "fans": 4, "review_count": 118, "average_stars": 3.56, "friends": [], "gender": "male", "age": 18}, {"user_id": "u-KFQJvl2ZfGZP44QuKr-0mQ", "name": "Hannah", "fans": 0, "review_count": 17, "average_stars": 4.0, "friends": [], "gender": "female", "age": 35}, {"user_id": "u-XzTkP0BJfEGwXpBssyrb6A", "name": "Shakti", "fans": 0, "review_count": 3, "average_stars": 1.33, "friends": [], "gender": "female", "age": 35}, {"user_id": "u-DFgGYfDFY1RxiWjxgV85lA", "name": "Aparna", "fans": 1, "review_count": 8, "average_stars": 3.5, "friends": [], "gender": "female", "age": 18}, {"user_id": "u-4pCvRmbz0jHoeo4kPisdCg", "name": "Sunil", "fans": 0, "review_count": 5, "average_stars": 3.17, "friends": [], "gender": "male", "age": 25}, {"user_id": "u-TwErSmI2nOF0UqXZ2tUDfQ", "name": "MyOne", "fans": 0, "review_count": 19, "average_stars": 3.19, "friends": [], "gender": "female", "age": 25}, {"user_id": "u-TZPd84Z7ATl5DqvTVJxDFw", "name": "Ritesh", "fans": 1, "review_count": 9, "average_stars": 2.27, "friends": [], "gender": "female", "age": 25}, {"user_id": "u-WcLp2MB0EloBPPEc5RDUAw", "name": "Indian", "fans": 0, "review_count": 9, "average_stars": 3.5, "friends": [], "gender": "female", "age": 1}, {"user_id": "u-OVFFbN9ij5wFL3UQLhT3pA", "name": "Deb", "fans": 0, "review_count": 2, "average_stars": 1.0, "friends": [], "gender": "female", "age": 18}, {"user_id": "u-JHCs-fyEMnKjWQkQvRSORQ", "name": "Ali", "fans": 0, "review_count": 33, "average_stars": 3.24, "friends": [], "gender": "male", "age": 35}, {"user_id": "u-7jw2VAbnGkr0GF6evuvViQ", "name": "Alon", "fans": 1, "review_count": 151, "average_stars": 3.54, "friends": [], "gender": "male", "age": 18}, {"user_id": "u-zHU5uBo_UMGao4wwwiTOfA", "name": "Miriam", "fans": 0, "review_count": 5, "average_stars": 5.0, "friends": [], "gender": "female", "age": 1}, {"user_id": "u-4W-ZU-E82HWWUNNk9tfN6g", "name": "A", "fans": 3, "review_count": 164, "average_stars": 3.56, "friends": [], "gender": "female", "age": 25}, {"user_id": "u-2mKI7s51PD-W5t8CrCRjNA", "name": "Kevin", "fans": 2, "review_count": 63, "average_stars": 4.48, "friends": [], "gender": "male", "age": 25}]